Workbook

Sheet Início
A1: Elaborado por: Chefe Fernando Mendes (contato: fernando.mendes@escoteiros.org.br)
A2: OBSERVAÇÕES IMPORTANTES!
A3: ESTE NÃO É UM DOCUMENTO OFICIAL DA UNIÃO DOS ESCOTEIROS DO BRASIL (UEB)
A4: As "equivalências" apontadas nesta planilha foram feitas por observações pessoais e subjetivas do criador desta planilha e podem não refletir o entendimento de outros escotistas, os quais farão as conversões/equiparações da progressão dos seus jovens conforme seus próprios entendimentos e critérios.
A5: Por se tratar de equiparações subjetivas e individualizadas para cada jovem, o escotista pode (e deve!) realizar outras alterações/equiparações conforme suas necessidades/entendimento, motivo pelo qual a presente planilha caso utilizada deve ser tratada apenas como um documento de orientação, e não como a verdade absoluta.
A6: Esta planilha só realiza equivalências dos itens da modalidade básica. (Os itens de progressão específicos das modalidades do Ar e do Mar, não foram verificados)
A7: Foi observado que alguns itens de progressão do programa atualizado "equivalem" à íntegra ou são muito similares a 100% de determinadas competências do programa anterior, portanto alguns itens do programa atualizado somente serão considerados OK nesta planilha caso o jovem tenha atingido 100% da competência do programa anterior
A8: As especialidades sofreram modificações no novo programa, algumas foram extintas e outras foram criadas. As especialidades de VOLEI e HANDEBOL, por exemplo, não existem mais. Contundo foi criada a especialidade ESPORTES DE QUADRA, que para esta planilha são equivalentes, ou seja, se o(a) jovem possui especialidade de volei ou handebol esta planilha valida o item de progressão como se tivesse a especialidade de esportes de quadra. Da mesma forma ocorre com as especialidades de GINÁSTIVA RITMICA e GINÁSTICA ARTÍSTICA, que não existem mais, porém existe a agora a especialidade de GINÁSTICAS.
A10: COMO UTILIZAR ESTA PLANILHA EM APENAS 5 PASSOS:
A12: 1º - Você precisará de um novo arquivo/planilha para cada jovem, portanto sugere-se deixar o arquivo original salvo em seu computador para utilizar como modelo. Na aba "Dados do Jovem" insira nas células em azul claro na coluna "B" o nome do(a) jovem e selecione a progressão em que ele(a) se encontra no programa antigo. Siga para o próximo passo.
A14: 2º - Na aba "PISTAS E TRILHAS" escolha na caixa de seleção se o(a) jovem já realizou 100% dos itens, neste caso a planilha preencherá os dados automaticamente OU caso não tenha realizado 100% dos itens: digite apenas o numeral "1" (sem as aspas) nas células em azul claro na coluna "A", ao lado dos itens que já foram realizados pelo jovem no programa antigo. Acesse o mAPPa ou o PAXTU para buscar estas informações. Na aba "RUMO E TRAVESSIA" digite apenas o numeral "1" (sem as aspas) nas células em azul claro na coluna "A", ao lado dos itens que já foram realizados pelo jovem no programa antigo. Acesse o mAPPa ou o PAXTU para buscar estas informações. Após inserir as informações nas abas "PISTAS E TRILHA" e "RUMO E TRAVESSIA" e siga para o próximo passo.
A16: 3º - Na aba "ESPECIALIDADES" digite apenas o numeral "1" (sem as aspas) nas células em azul claro ao lado do nome das insígnias e/ou distintivos e/ou respectivas especialidades já conquistadas pelo jovem. Feito isso siga para o próximo passo.
... A22: Eu não concordo com uma ou mais equivalências feitas automaticamnte pela planilha E/OU quero validar um item que acabei de conversar com o(a) jovem para chegar na progressar correta? Como fazer? Se você não concorda com a equivalência automática feita pela planilha você pode desmarcar o item manualmente inserindo o numeral "-1" (um negativo, sem aspas) na célula em azul claro ao lado direito do respectivo item. Feito isto o item não será considerado cumprido pelo(a) jovem. Para validar manualmente um item de progressão basta digitar o numeral "1" (sem aspas) na célula em azul claro ao lado direito do respectivo item. Feito isto o item será validado e considerado como cumprido. Caso resolva retornar para o sistema automatizado pela planilha, basta deixar novamente a célula em azul claro sem nenhum preenchimento (vazia). Feito isso a planilha voltará a considerar apenas a conversão/equiparação automática daquele item.

Sheet Dados do Jovem
A1: Nome do(a) jovem: | C1: Selecione aqui progressão
A2: Progressão programa antigo: | B2: Selecione aqui progressão | C2: PISTAS
C3: TRILHA
A4: Blocos educacionais concluídos: | B4: ='Habilidades para a Vida'!I3+'Meio Ambiente'!I3+'Paz e Desenvolvimento'!G3+'Saúde e Bem Estar'!G3 -> 0 | C4: RUMO
C5: TRAVESSIA
A6: Progressão no novo programa: | B6: =IF(B4<=3,"PISTAS",IF(B4<=7,"TRILHA",IF(B4<=12,"RUMO","TRAVESSIA"))) -> PISTAS
B7: =IF(B6=B2,"Equipação OK","Necessário adaptar itens") -> Necessário adaptar itens

Sheet Pistas e Trilha
C1: PISTAS E TRILHA
C2: Selecione na célula abaixo: o(a) jovem já concluiu todos os itens de Pistas e Trilhas?
C3: Não concluiu 100% dos itens | E3: Sim, já concluiu 100% dos itens
C4: =IF(C3="Não concluiu 100% dos itens","Marcar abaixo apenas o numeral 1 (sem as aspas) nas células em azul claro na coluna A, ao lado dos itens que já foram realizados pelo jovem no programa antigo","OK, todos os itens desta aba foram marcados automaticamente") -> Marcar abaixo apenas o numeral 1 (sem as aspas) nas células em azul claro na coluna A, ao lado dos itens que já foram realizados pelo jovem no programa antigo | E4: Não concluiu 100% dos itens
C6: FÍSICO
A7: =IF(A11=3,1,0) -> 0 | C7: Percebo que meu corpo está mudando, e faço atividades que o ajudam a ser forte e sadio, evitando aquilo que pode me fazer mal.
A8: =IF($C$3="Sim, já concluiu 100% dos itens",1,0) -> 0 | B8: 1 | C8: Participar de pelo menos 5 atividades ao ar livre da patrulha (jornadas, excursões, acampamentos de patrulha ou tropa) utilizando normas de baixo impacto ambiental.
A9: =IF($C$3="Sim, já concluiu 100% dos itens",1,0) -> 0 | B9: 2 | C9: Conhecer e aplicar normas de limpeza no tratamento e na conservação de alimentos nas atividades de patrulha.
A10: =IF($C$3="Sim, já concluiu 100% dos itens",1,0) -> 0 | B10: 3 | C10: Aferir seu passo duplo, conhecer as medidas de seu corpo e aplicar-las em avaliações e medições.
A11: =SUM(A8:A10) -> 0
A12: =IF(A17=4,1,0) -> 0 | C12: Participo das atividades organizadas por minha patrulha cuidando para não colocar em risco minha saúde e a de meus companheiros.
A13: =IF($C$3="Sim, já concluiu 100% dos itens",1,0) -> 0 | B13: 4 | C13: Conhecer os elementos que compõem a caixa de primeiros socorros da patrulha.
A14: =IF($C$3="Sim, já concluiu 100% dos itens",1,0) -> 0 | B14: 5 | C14: Conhecer as ações iniciais que devem ser tomadas num acidente e saber como cuidar de ferimentos leves; bandagens e transporte de feridos, pequenos cortes e insetos
A15: =IF($C$3="Sim, já concluiu 100% dos itens",1,0) -> 0 | B15: 6 | C15: Aplicar medidas de segurança nas atividades de patrulha e tropa.
A16: =IF($C$3="Sim, já concluiu 100% dos itens",1,0) -> 0 | B16: 7 | C16: Saber como prevenir os males da exposição ao sol: insolação, desidratação, queimaduras, câncer de pele.
A17: =SUM(A13:A16) -> 0
A18: =IF(A23=4,1,0) -> 0 | C18: Mantenho limpo e arrumado o ambiente em que faço minhas coisas, e cuido da minha higiene e apresentação pessoal.
A19: =IF($C$3="Sim, já concluiu 100% dos itens",1,0) -> 0 | B19: 8 | C19: Manter hábitos de higiene individual, demonstrar cuidado com o vestuário ou uniforme escoteiro e utilizar corretamente os distintivos e emblemas.
A20: =IF($C$3="Sim, já concluiu 100% dos itens",1,0) -> 0 | B20: 9 | C20: Classificar o lixo em diferentes categorias e saber como tratar os diferentes tipos de resíduos de acampamentos ou excursões utilizando “engenhocas” para melhorar a higiene e o conforto nos acampamentos.
A21: =IF($C$3="Sim, já concluiu 100% dos itens",1,0) -> 0 | B21: 10 | C21: Participar da manutenção do canto de patrulha, conhecer os materiais de sua patrulha e contribuir para a sua conservação, organização e limpeza.
A22: =IF($C$3="Sim, já concluiu 100% dos itens",1,0) -> 0 | B22: 11 | C22: Montar corretamente uma mochila para um acampamento de 3 dias e manter seu equipamento pessoal em bom estado.
A23: =SUM(A19:A22) -> 0
A24: =IF(A29=4,1,0) -> 0 | C24: Como alimentos saudáveis, nas horas certas, e cuido da limpeza ao preparar refeições.
A25: =IF($C$3="Sim, já concluiu 100% dos itens",1,0) -> 0 | B25: 12 | C25: Montar o cardápio de uma jornada e durante as atividades de sua patrulha, fazer as refeições de maneira equilibrada.
A26: =IF($C$3="Sim, já concluiu 100% dos itens",1,0) -> 0 | B26: 13 | C26: Colaborar na elaboração de alimentos (como cozinheiro ou copeiro) em pelo menos três atividades ao ar livre da patrulha; (jornadas, excursões ou acampamento de patrulha).
A27: =IF($C$3="Sim, já concluiu 100% dos itens",1,0) -> 0 | B27: 14 | C27: Montar uma solução para purificação de água em acampamentos
A28: =IF($C$3="Sim, já concluiu 100% dos itens",1,0) -> 0 | B28: 15 | C28: Utilizar diversos tipos de fogos de acampamento, de maneira adequada e segura.
A29: =SUM(A25:A28) -> 0
A30: =IF(A34=3,1,0) -> 0 | C30: Dedico ao estudo tempo suficiente, e uso meu tempo livre para participar de atividades recreativas e variadas.
A31: =IF($C$3="Sim, já concluiu 100% dos itens",1,0) -> 0 | B31: 16 | C31: Organizar seu tempo utilizando uma agenda ou instrumento similar.
A32: =IF($C$3="Sim, já concluiu 100% dos itens",1,0) -> 0 | B32: 17 | C32: Realizar, dentro do prazo, as suas tarefas escolares
A33: =IF($C$3="Sim, já concluiu 100% dos itens",1,0) -> 0 | B33: 18 | C33: Frequentar regularmente as atividades e reuniões da sua patrulha e da tropa.
A34: =SUM(A31:A33) -> 0
A35: =IF(A38=2,1,0) -> 0 | C35: Pratico atividades físicas regularmente e participo de muitos jogos, respeitando as suas regras e os demais participantes.
A36: =IF($C$3="Sim, já concluiu 100% dos itens",1,0) -> 0 | B36: 19 | C36: Realizar regularmente uma atividade física ou o esporte que escolheu.
A37: =IF($C$3="Sim, já concluiu 100% dos itens",1,0) -> 0 | B37: 20 | C37: Participar de diversos jogos com sua patrulha e tropa respeitando as regras e aos demais participantes.
A38: =SUM(A36:A37) -> 0
C39: INTELECTUAL
A40: =IF(A44=3,1,0) -> 0 | C40: Interesso-me pelo que se passa a minha volta e estou sempre disposto a aprender coisas novas.
A41: =IF($C$3="Sim, já concluiu 100% dos itens",1,0) -> 0 | B41: 21 | C41: Traçar e seguir sinais de pista em um percurso de pelo menos 500 metros em área de campo, e pelo menos 1.000 metros em área urbana.
A42: =IF($C$3="Sim, já concluiu 100% dos itens",1,0) -> 0 | B42: 22 | C42: Utilizar um mapa e uma bússola para orientar-se.
A43: =IF($C$3="Sim, já concluiu 100% dos itens",1,0) -> 0 | B43: 23 | C43: Aplicar as técnicas de “tocaia” em um jogo com sua patrulha ou tropa.
A44: =SUM(A41:A43) -> 0
A45: =IF(A50=4,1,0) -> 0 | C45: Sei buscar informações que me ajudam a analisar problemas e encontrar soluções, procurando minhas próprias leituras e relacionando com as coisas que me acontecem.
A46: =IF($C$3="Sim, já concluiu 100% dos itens",1,0) -> 0 | B46: 24 | C46: Explorar com sua patrulha ou tropa a comunidade onde vive, identificando problemas e buscando soluções.
A47: =IF($C$3="Sim, já concluiu 100% dos itens",1,0) -> 0 | B47: 25 | C47: Estimar altura e distâncias utilizando distintos métodos.
A48: =IF($C$3="Sim, já concluiu 100% dos itens",1,0) -> 0 | B48: 26 | C48: Ler um livro e após a leitura apresentar um resumo a patrulha.
A49: =IF($C$3="Sim, já concluiu 100% dos itens",1,0) -> 0 | B49: 27 | C49: Saber utilizar alguma técnica de previsão do tempo por indícios naturais.
A50: =SUM(A46:A49) -> 0
A51: =IF(A56=4,1,0) -> 0 | C51: Participo das atividades decididas por meu grupo de amigos, contribuindo nas discussões, manifestando minhas ideias e experiências.
A52: =IF($C$3="Sim, já concluiu 100% dos itens",1,0) -> 0 | B52: 28 | C52: Participar de, pelo menos, dois jogos democráticos de sua tropa.
A53: =IF($C$3="Sim, já concluiu 100% dos itens",1,0) -> 0 | B53: 29 | C53: Participar ativamente de seu conselho de patrulha contribuindo com ideias e pontos de vista.
A54: =IF($C$3="Sim, já concluiu 100% dos itens",1,0) -> 0 | B54: 30 | C54: Participar da organização e planejamento de uma excursão de patrulha; e contribuir com ideias para as atividades de patrulha ou tropa.
A55: =IF($C$3="Sim, já concluiu 100% dos itens",1,0) -> 0 | B55: 31 | C55: Avaliar as atividades juntamente com sua patrulha ou tropa.
A56: =SUM(A52:A55) -> 0
A57: =IF(A60=2,1,0) -> 0 | C57: Conheço as especialidades e as utilizo sempre que necessário.
A58: =IF($C$3="Sim, já concluiu 100% dos itens",1,0) -> 0 | B58: 32 | C58: Demonstrar que utiliza as especialidades que conquista para colaborar em sua patrulha, casa ou escola.
A59: =IF($C$3="Sim, já concluiu 100% dos itens",1,0) -> 0 | B59: 33 | C59: Ajudar um escoteiro da patrulha a conquistar uma especialidade.
A60: =SUM(A58:A59) -> 0
A61: =IF(A65=3,1,0) -> 0 | C61: Participo com entusiasmo das atividades artísticas de minha tropa.
A62: =IF($C$3="Sim, já concluiu 100% dos itens",1,0) -> 0 | B62: 34 | C62: Participar de um fogo de conselho e de uma apresentação com sua patrulha.
A63: =IF($C$3="Sim, já concluiu 100% dos itens",1,0) -> 0 | B63: 35 | C63: Construir, com sucata, um instrumento musical.
A64: =IF($C$3="Sim, já concluiu 100% dos itens",1,0) -> 0 | B64: 36 | C64: Conhecer e cantar algumas canções e danças tradicionais do Movimento Escoteiro e de sua tropa, em especial, o Hino Alerta.
A65: =SUM(A62:A64) -> 0
A66: =IF(A70=3,1,0) -> 0 | C66: Conheço várias técnicas de comunicação e sei utilizar algumas delas.
A67: =IF($C$3="Sim, já concluiu 100% dos itens",1,0) -> 0 | B67: 37 | C67: Ler e escrever mensagens usando um código secreto de sua patrulha.
A68: =IF($C$3="Sim, já concluiu 100% dos itens",1,0) -> 0 | B68: 38 | C68: Utilizar corretamente um rádio comunicador numa atividade de sua patrulha.
A69: =IF($C$3="Sim, já concluiu 100% dos itens",1,0) -> 0 | B69: 39 | C69: Montar um blog, lista de e-mails ou projeto similar que contribua para melhorar a comunicação em sua patrulha ou tropa.
A70: =SUM(A67:A69) -> 0
A71: =IF(A75=3,1,0) -> 0 | C71: Procuro desenvolver minhas habilidades manuais.
A72: =IF($C$3="Sim, já concluiu 100% dos itens",1,0) -> 0 | B72: 40 | C72: Participar ativamente da construção de pioneiras num acampamento de tropa, aplicando pelo menos os seguintes nós e amarras: direito, volta do fiel ou volta da ribeira, nó de escota, amarra quadrada e diagonal.
A73: =IF($C$3="Sim, já concluiu 100% dos itens",1,0) -> 0 | B73: 41 | C73: Saber utilizar e conservar as ferramentas típicas de uma patrulha (machadinha, facão, etc.) e demonstrar os cuidados básicos com os utensílios de campo (como lampiões e fogareiros).
A74: =IF($C$3="Sim, já concluiu 100% dos itens",1,0) -> 0 | B74: 42 | C74: Participar da construção de um fogão suspenso ou forno de acampamento.
A75: =SUM(A72:A74) -> 0
C76: CARÁTER
A77: =IF(A81=3,1,0) -> 0 | C77: Procuro me conhecer cada vez mais, analisando as críticas que recebo e definindo ações para melhorar dia a dia.
A78: =IF($C$3="Sim, já concluiu 100% dos itens",1,0) -> 0 | B78: 43 | C78: Propor objetivos e ações para melhorar em alguns aspectos da sua vida.
A79: =IF($C$3="Sim, já concluiu 100% dos itens",1,0) -> 0 | B79: 44 | C79: Participar da avaliação de sua progressão pessoal e das de seus companheiros em conselho de patrulha.
A80: =IF($C$3="Sim, já concluiu 100% dos itens",1,0) -> 0 | B80: 45 | C80: Avaliar o seu desempenho e o de seus companheiros nos cargos de patrulha.
A81: =SUM(A78:A80) -> 0
A82: =IF(A85=2,1,0) -> 0 | C82: Compreendo a Lei e a Promessa Escoteira, e estou sempre disposto a aplicá-las em minha vida.
A83: =IF($C$3="Sim, já concluiu 100% dos itens",1,0) -> 0 | B83: 46 | C83: Explicar o significado da Lei e da Promessa Escoteiras aos novos integrantes da sua patrulha.
A84: =IF($C$3="Sim, já concluiu 100% dos itens",1,0) -> 0 | B84: 47 | C84: Participar corretamente das cerimônias com os símbolos nacionais e saber cantar o Hino Nacional.
A85: =SUM(A83:A84) -> 0
A86: =IF(A89=2,1,0) -> 0 | C86: Sei o que significa lealdade e procuro agir desta forma com os outros e comigo mesmo.
A87: =IF($C$3="Sim, já concluiu 100% dos itens",1,0) -> 0 | B87: 48 | C87: Explicar, a partir do seu ponto de vista, o que significa ser leal.
A88: =IF($C$3="Sim, já concluiu 100% dos itens",1,0) -> 0 | B88: 49 | C88: Aplicar o conceito de lealdade em jogos e atividades de sua patrulha e tropa.
A89: =SUM(A87:A88) -> 0
A90: =IF(A93=2,1,0) -> 0 | C90: Procuro ser alegre, mesmo nos momentos difíceis, compartilho minha alegria com os outros respeitando a todos.
A91: =IF($C$3="Sim, já concluiu 100% dos itens",1,0) -> 0 | B91: 50 | C91: Participar como animador em um acampamento de sua patrulha.
A92: =IF($C$3="Sim, já concluiu 100% dos itens",1,0) -> 0 | B92: 51 | C92: Conhecer historias de pessoas que se sobrepuseram em momentos difíceis e os relatar aos seus companheiros de patrulha.
A93: =SUM(A91:A92) -> 0
A94: =IF(A98=3,1,0) -> 0 | C94: Escuto os conselhos que recebo do meu grupo de amigos e respeito as decisões que tomamos, mesmo quando penso de maneira diferente.
A95: =IF($C$3="Sim, já concluiu 100% dos itens",1,0) -> 0 | B95: 52 | C95: Respeitar e apoiar as decisões tomadas no conselho de patrulha, ainda que não esteja de acordo.
A96: =IF($C$3="Sim, já concluiu 100% dos itens",1,0) -> 0 | B96: 53 | C96: Ajudar a melhorar a organização de seu conselho de patrulha.
A97: =IF($C$3="Sim, já concluiu 100% dos itens",1,0) -> 0 | B97: 54 | C97: Participar da eleição do monitor da sua patrulha.
A98: =SUM(A95:A97) -> 0
C99: AFETIVO
A100: =IF(A105=4,1,0) -> 0 | C100: Compreendo meus sentimentos e sei a quem procurar quando estou triste e confuso.
A101: =IF($C$3="Sim, já concluiu 100% dos itens",1,0) -> 0 | B101: 55 | C101: Pesquisar os malefícios de drogas e entorpecentes.
...

Sheet Rumo e Travessia
C1: RUMO E TRAVESSIA
C2: Marcar abaixo apenas o numeral "1" (sem as aspas) nas células em azul claro na coluna "A", ao lado dos itens que já foram realizados pelo jovem no programa antigo
C4: FÍSICO
A5: =IF(A9=3,1,0) -> 0 | C5: Respeito meu corpo e o dos outros, entendo as mudanças que estão acontecendo, como me afetam e procuro superar as dificuldades físicas próprias de meu crescimento.
B6: 1 | C6: Participar de pelo menos 5 atividades ao ar livre da patrulha (acampamentos ou excursões) utilizando normas de baixo impacto ambiental.
B7: 2 | C7: Saber explicar as mudanças que estão acontecendo no seu corpo; conhecer os males da anorexia, bulimia, os perigos do álcool e cigarro e manter hábitos de higiene pessoal.
B8: 3 | C8: Participar de uma Jornada de Travessia.
A9: =SUM(A6:A8) -> 0
A10: =IF(A15=4,1,0) -> 0 | C10: Sei o que fazer em caso de uma enfermidade ou acidente.
B11: 4 | C11: Reconhecer os tipos mais comuns de animais venenosos e peçonhentos de sua região.
B12: 5 | C12: Manter em dia os elementos que compõem a caixa de primeiros socorros da patrulha.
B13: 6 | C13: Aplicar medidas gerais de segurança em caso de acidentes, e saber determinar a ordem de prioridades quando assistir a um acidente e utilizar distintas técnicas para o transporte de feridos.
B14: 7 | C14: Saber agir em casos de hemorragia
A15: =SUM(A11:A14) -> 0
A16: =IF(A21=4,1,0) -> 0 | C16: Mantenho minhas coisas limpas e organizadas, cuido dos lugares que visito e da minha apresentação pessoal.
B17: 8 | C17: Participar de uma atividade de limpeza e organização do canto de patrulha (em sede).
B18: 9 | C18: Propor e executar uma atividade de melhoria em algum local visitado pela patrulha em acampamentos e manter em ordem seu quarto e objetos pessoais.
B19: 10 | C19: Demonstrar cuidado com seu vestuário ou uniforme escoteiro e costurar os seus distintivos e insígnias
B20: 11 | C20: Montar corretamente uma mochila para um acampamento de cinco dias e manter o equipamentos de sua patrulha em bom estado.
A21: =SUM(A17:A20) -> 0
A22: =IF(A26=3,1,0) -> 0 | C22: Sei preparar uma refeição com ordem e limpeza, considerando os valores dos alimentos e suas contribuições para o saúde.
B23: 12 | C23: Preparar cinco refeições para sua patrulha, incluindo a preparação de um prato quente e de uma sobremesa sendo três refeições em fogueira ou fogão de campo.
B24: 13 | C24: Montar o cardápio de um acampamento de patrulha de fim de semana e fazer as refeições de maneira equilibrada, durante as atividades de patrulha.
B25: 14 | C25: Cozinhar ao ar livre sem utensílios (comida mateira), respeitando as normas de limpeza
A26: =SUM(A23:A25) -> 0
A27: =IF(A32=4,1,0) -> 0 | C27: Sei distribuir meu tempo para atividades de estudo, convivência familiar, com amigos e sei escolher o que fazer no meu tempo livre.
B28: 15 | C28: Organizar suas atividades em um calendário semanal.
B29: 16 | C29: Classificar suas atividades segundo um critério de prioridades.
B30: 17 | C30: Participar regularmente das atividades e reuniões de sua patrulha, contribuindo com ideias e sugestões para as atividades.
B31: 18 | C31: Desenvolver um passatempo ou hobbie.
A32: =SUM(A28:A31) -> 0
A33: =IF(A36=2,1,0) -> 0 | C33: Me esforço para melhorar meu desempenho nas atividades físicas que pratico
B34: 19 | C34: Realizar regularmente uma atividade física ou esporte, demonstrando progresso em seu desempenho
B35: 20 | C35: Participar de diversos jogos com outros grupos escoteiros, respeitando as regras e os demais participantes.
A36: =SUM(A34:A35) -> 0
C37: INTELECTUAL
A38: =IF(A43=4,1,0) -> 0 | C38: Procuro ampliar meus conhecimentos e sei refletir criticamente sobre os fatos que ocorrem em minha volta, e me interesso pela leitura de diversos temas.
B39: 21 | C39: Realizar previsão do tempo por indícios naturais e por instrumentos.
B40: 22 | C40: Traçar e seguir sinais de pista em um percurso de, pelo menos, 1 km no campo ou 2 km em área urbana
B41: 23 | C41: Orientar-se utilizando recursos naturais (estrelas, método do relógio), assim como usando uma bússola e um mapa
B42: 24 | C42: Ler pelo menos um capítulo do livro “Escotismo para Rapazes”
A43: =SUM(A39:A42) -> 0
A44: =IF(A49=4,1,0) -> 0 | C44: Posso analisar uma situação a partir de diferentes pontos de vista estimulando meus amigos para que façam o mesmo.
B45: 25 | C45: Participar de, pelo menos, três jogos democráticos da tropa.
B46: 26 | C46: Participar da avaliação de uma atividade regional.
B47: 27 | C47: Explorar algum tema de seu interesse e compartilho com sua patrulha ou tropa
B48: 28 | C48: Aplicar técnicas de medição de distância ou altura em uma atividade de patrulha ou tropa.
A49: =SUM(A45:A48) -> 0
A50: =IF(A55=4,1,0) -> 0 | C50: Organizo atividades criativas para serem realizadas com meu grupo de amigos.
B51: 29 | C51: Preparar materiais para as representações artísticas de sua patrulha ou tropa.
B52: 30 | C52: Organizar um dia de jogos na casa de um companheiro de patrulha.
B53: 31 | C53: Propor e colaborar na organização de atividades de sua patrulha e tropa
B54: 32 | C54: Organizar no seu colégio uma atividade de divulgação do grupo escoteiro.
A55: =SUM(A51:A54) -> 0
A56: =IF(A60=3,1,0) -> 0 | C56: Amplio meus conhecimentos nas especialidades que escolhi, usando-as em ações a serviço da comunidade.
B57: 33 | C57: Aplicar as especialidades em ações de serviço da comunidade.
B58: 34 | C58: Ajudar a outros jovens na conquista das especialidades
B59: 35 | C59: Propor a sua patrulha e tropa ideias de ações a serviço da comunidade
A60: =SUM(A57:A59) -> 0
A61: =IF(A65=3,1,0) -> 0 | C61: Manifesto meus interesses e aptidões artísticas, contribuindo com o bom ambiente nas atividades.
B62: 36 | C62: Ser responsável por apresentar as canções, durante o fogo de conselho de um acampamento de tropa.
B63: 37 | C63: Organizar e participar um esquete de um fogo de conselho da tropa.
B64: 38 | C64: Ensinar a outros escoteiros algumas canções tradicionais do movimento.
A65: =SUM(A62:A64) -> 0
A66: =IF(A71=4,1,0) -> 0 | C66: Proponho e participo de projetos que apresentam soluções criativas para problemas técnicos habituais.
B67: 39 | C67: Construir um fogão solar e utilizar para uma refeição em um acampamento de patrulha ou tropa.
B68: 40 | C68: Construir um chuveiro de acampamento.
B69: 41 | C69: Saber como funcionam os serviços que uso (telefone, internet, rádio, TV...) e procuro usar estes conhecimentos para solucionar problemas técnicos habituais.
B70: 42 | C70: Conhecer e ser capaz de enviar e receber mensagens simples com uma das seguintes formas de comunicação: morse, semáfora, LIBRAS
A71: =SUM(A67:A70) -> 0
A72: =IF(A77=4,1,0) -> 0 | C72: Melhoro minhas habilidades manuais.
B73: 43 | C73: Desenhar um croqui de um lugar de acampamento utilizando sinais topográficos, e participar do projeto e instalação das pioneirias de acampamento, aplicando pelo menos os seguintes nós e amarras: direito, volta do fiel ou volta da ribeira, nó de escota, nó em oito, volta redonda com dois cotes, amarra quadrada e diagonal.
B74: 44 | C74: Aplicar os conceitos básicos de estruturas (cavaletes, encaixes, ancoragens) nos projetos e montagem de construções como pontes, balsas, etc.
B75: 45 | C75: Confeccionar “falcaças”, nó “catau”, laís de guia, cadeira de bombeiro e demonstrar os cuidados básicos com as cordas.
B76: 46 | C76: Construir e pernoitar em um abrigo natural.
A77: =SUM(A73:A76) -> 0
C78: CARÁTER
A79: =IF(A84=4,1,0) -> 0 | C79: Sei fazer uma auto-avaliação e procuro ser cada vez melhor, ajudando meus amigos a fazerem o mesmo
B80: 47 | C80: Propor objetivos e ações para melhorar em alguns aspectos de sua vida na tropa.
B81: 48 | C81: Participar ativamente na avaliação de sua progressão pessoal e de seus companheiros no conselho de patrulha
B82: 49 | C82: Participar de uma reunião onde são tratados os aspectos positivos e negativos de sua patrulha.
B83: 50 | C83: Ajudar a um companheiro em sua progressão pessoal.
A84: =SUM(A80:A83) -> 0
A85: =IF(A90=4,1,0) -> 0 | C85: Busco fazer as coisas bem feitas, superando minhas limitações para cumprir minhas responsabilidades.
B86: 51 | C86: Desempenhar um cargo de patrulha por pelo menos um ciclo de programa
B87: 52 | C87: Capacitar-se para desempenhar seu cargo na patrulha.
B88: 53 | C88: Avaliar seu desempenho e de seus amigos nos cargos de patrulha.
B89: 54 | C89: Participar de um festival de talentos na tropa.
A90: =SUM(A86:A89) -> 0
A91: =IF(A95=3,1,0) -> 0 | C91: Compreendo o valor da Lei e da Promessa em minha vida e me esforço para vivê-las plenamente.
B92: 55 | C92: Auxiliar um companheiro de patrulha a realizar sua Promessa escoteira
B93: 56 | C93: Avaliar com seus companheiros a vivência da Promessa e Lei Escoteiras na patrulha.
B94: 57 | C94: Cantar com sua patrulha a Canção da Promessa
A95: =SUM(A92:A94) -> 0
A96: =IF(A99=2,1,0) -> 0 | C96: Entendo que é importante ser verdadeiro, agindo de acordo com o que se pensa e se comprometendo com aquilo em que se acredita.
B97: 58 | C97: Conhecer a história de Caio Viana Martins
B98: 59 | C98: Realizar boas ações pessoais e junto com sua patrulha.
A99: =SUM(A97:A98) -> 0
A100: =IF(A104=3,1,0) -> 0 | C100: Estou sempre alegre e divido minha alegria com os outros
B101: 60 | C101: Organizar uma “oficina de brinquedos” com sua patrulha, doando os itens consertados para uma instituição de crianças carentes.
...

Sheet Especialidades ou Insígnias
A1: INSTRUÇÕES: apenas digite o numeral "1" (sem aspas) na célula em azul claro ao lado do nome da especialidade, ou Insíginia já conquistada pelo jovem no programa antigo
A3: pare o mouse/cursor aqui para abrir informações adicionais
B5: Prog. Antigo | F5: Prog. Novo
A6: Especialidade / Insígnia Especial | B6: Nível 1 | C6: Nível 2 | D6: Nível 3 | F6: Nível 1 | G6: Nível 2
A7: Acampamento | F7: =IF(B7>0,1,0) -> 0 | G7: =IF(OR(C7>0,D7>0),"1","") | H7: =IF(OR(C7=1,D7=1),1,0) -> 0
A8: Acampamento de Mínimo Impacto | F8: =IF(B8>0,1,0) -> 0 | G8: =IF(OR(C8>0,D8>0),"1","") | H8: =IF(OR(C8=1,D8=1),1,0) -> 0
A9: Administração | F9: =IF(B9>0,1,0) -> 0 | G9: =IF(OR(C9>0,D9>0),"1","") | H9: =IF(OR(C9=1,D9=1),1,0) -> 0
A10: Aeromodelismo | F10: =IF(B10>0,1,0) -> 0 | G10: =IF(OR(C10>0,D10>0),"1","") | H10: =IF(OR(C10=1,D10=1),1,0) -> 0
A11: Agricultura | F11: =IF(B11>0,1,0) -> 0 | G11: =IF(OR(C11>0,D11>0),"1","") | H11: =IF(OR(C11=1,D11=1),1,0) -> 0
A12: Alfabetização | F12: =IF(B12>0,1,0) -> 0 | G12: =IF(OR(C12>0,D12>0),"1","") | H12: =IF(OR(C12=1,D12=1),1,0) -> 0
A13: Almoxarifado | F13: =IF(B13>0,1,0) -> 0 | G13: =IF(OR(C13>0,D13>0),"1","") | H13: =IF(OR(C13=1,D13=1),1,0) -> 0
A14: Anatomia Humana | F14: =IF(B14>0,1,0) -> 0 | G14: =IF(OR(C14>0,D14>0),"1","") | H14: =IF(OR(C14=1,D14=1),1,0) -> 0
A15: Animação da Fé | F15: =IF(B15>0,1,0) -> 0 | G15: =IF(OR(C15>0,D15>0),"1","") | H15: =IF(OR(C15=1,D15=1),1,0) -> 0
A16: Animais Peçonhentos (Equiparação com a nova: Animais Venenosos e Peçonhentos) | F16: =IF(B16>0,1,0) -> 0 | G16: =IF(OR(C16>0,D16>0),"1","") | H16: =IF(OR(C16=1,D16=1),1,0) -> 0
A17: Anime | F17: =IF(B17>0,1,0) -> 0 | G17: =IF(OR(C17>0,D17>0),"1","") | H17: =IF(OR(C17=1,D17=1),1,0) -> 0
A18: Aquariofilia | F18: =IF(B18>0,1,0) -> 0 | G18: =IF(OR(C18>0,D18>0),"1","") | H18: =IF(OR(C18=1,D18=1),1,0) -> 0
... A114: Expressão Musical | F114: =IF(B114>0,1,0) -> 0 | G114: =IF(OR(C114>0,D114>0),"1","") | H114: =IF(OR(C114=1,D114=1),1,0) -> 0
A115: Explorador | F115: =IF(B115>0,1,0) -> 0
A116: Faixa do Cidadão | F116: =IF(B116>0,1,0) -> 0 | G116: =IF(OR(C116>0,D116>0),"1","") | H116: =IF(OR(C116=1,D116=1),1,0) -> 0
A117: Ferramentas de Corte | F117: =IF(B117>0,1,0) -> 0 | G117: =IF(OR(C117>0,D117>0),"1","") | H117: =IF(OR(C117=1,D117=1),1,0) -> 0
A118: Fiscalização de Pátio de Aeródromo | F118: =IF(B118>0,1,0) -> 0 | G118: =IF(OR(C118>0,D118>0),"1","") | H118: =IF(OR(C118=1,D118=1),1,0) -> 0
A119: Fogo de Conselho | F119: =IF(B119>0,1,0) -> 0 | G119: =IF(OR(C119>0,D119>0),"1","") | H119: =IF(OR(C119=1,D119=1),1,0) -> 0
A120: Fotografia | F120: =IF(B120>0,1,0) -> 0 | G120: =IF(OR(C120>0,D120>0),"1","") | H120: =IF(OR(C120=1,D120=1),1,0) -> 0
A121: Fotografia Digital | F121: =IF(B121>0,1,0) -> 0 | G121: =IF(OR(C121>0,D121>0),"1","") | H121: =IF(OR(C121=1,D121=1),1,0) -> 0
A122: Futebol | F122: =IF(B122>0,1,0) -> 0 | G122: =IF(OR(C122>0,D122>0),"1","") | H122: =IF(OR(C122=1,D122=1),1,0) -> 0
A123: Futebol de Mesa | F123: =IF(B123>0,1,0) -> 0 | G123: =IF(OR(C123>0,D123>0),"1","") | H123: =IF(OR(C123=1,D123=1),1,0) -> 0
A124: Gamão | F124: =IF(B124>0,1,0) -> 0 | G124: =IF(OR(C124>0,D124>0),"1","") | H124: =IF(OR(C124=1,D124=1),1,0) -> 0
A125: Garçom | F125: =IF(B125>0,1,0) -> 0 | G125: =IF(OR(C125>0,D125>0),"1","") | H125: =IF(OR(C125=1,D125=1),1,0) -> 0
A126: Genealogia | F126: =IF(B126>0,1,0) -> 0 | G126: =IF(OR(C126>0,D126>0),"1","") | H126: =IF(OR(C126=1,D126=1),1,0) -> 0
A127: Gênero Musical (antigo Rock) | F127: =IF(B127>0,1,0) -> 0 | G127: =IF(OR(C127>0,D127>0),"1","") | H127: =IF(OR(C127=1,D127=1),1,0) -> 0
... A154: Informática | F154: =IF(B154>0,1,0) -> 0 | G154: =IF(OR(C154>0,D154>0),"1","") | H154: =IF(OR(C154=1,D154=1),1,0) -> 0
A155: Insígnia Campeões da Natureza | F155: =IF(B155>0,1,0) -> 0
A156: Insígnia da Ação Comunitária | F156: =IF(B156>0,1,0) -> 0
A157: Insígnia da Lusofonia | F157: =IF(B157>0,1,0) -> 0
A158: Insígnia da Modalidade do Ar - Aviador | F158: =IF(B158>0,1,0) -> 0
A159: Insígnia da Modalidade do Mar - Grumete | F159: =IF(B159>0,1,0) -> 0
A160: Insígnia do Aprender | F160: =IF(B160>0,1,0) -> 0
A161: Insígnia do Cone Sul | F161: =IF(B161>0,1,0) -> 0
A162: Insígnia Escoteiros pela Energia Solar | F162: =IF(B162>0,1,0) -> 0
A163: Reduzir, Reciclar Reutilizar | F163: =IF(B163>0,1,0) -> 0
A164: Internet | F164: =IF(B164>0,1,0) -> 0 | G164: =IF(OR(C164>0,D164>0),"1","") | H164: =IF(OR(C164=1,D164=1),1,0) -> 0
A165: Invenção | F165: =IF(B165>0,1,0) -> 0 | G165: =IF(OR(C165>0,D165>0),"1","") | H165: =IF(OR(C165=1,D165=1),1,0) -> 0
A166: Investigação | F166: =IF(B166>0,1,0) -> 0 | G166: =IF(OR(C166>0,D166>0),"1","") | H166: =IF(OR(C166=1,D166=1),1,0) -> 0
A167: Investimentos | F167: =IF(B167>0,1,0) -> 0 | G167: =IF(OR(C167>0,D167>0),"1","") | H167: =IF(OR(C167=1,D167=1),1,0) -> 0
A168: Ioiô | F168: =IF(B168>0,1,0) -> 0 | G168: =IF(OR(C168>0,D168>0),"1","") | H168: =IF(OR(C168=1,D168=1),1,0) -> 0
A169: Jardinagem | F169: =IF(B169>0,1,0) -> 0 | G169: =IF(OR(C169>0,D169>0),"1","") | H169: =IF(OR(C169=1,D169=1),1,0) -> 0
A170: Jogos de Cartas Colecionáveis | F170: =IF(B170>0,1,0) -> 0 | G170: =IF(OR(C170>0,D170>0),"1","") | H170: =IF(OR(C170=1,D170=1),1,0) -> 0
A171: Jogos de Tabuleiro | F171: =IF(B171>0,1,0) -> 0 | G171: =IF(OR(C171>0,D171>0),"1","") | H171: =IF(OR(C171=1,D171=1),1,0) -> 0
A172: Jornalismo | F172: =IF(B172>0,1,0) -> 0 | G172: =IF(OR(C172>0,D172>0),"1","") | H172: =IF(OR(C172=1,D172=1),1,0) -> 0
A173: Leis | F173: =IF(B173>0,1,0) -> 0 | G173: =IF(OR(C173>0,D173>0),"1","") | H173: =IF(OR(C173=1,D173=1),1,0) -> 0
A174: Leitura | F174: =IF(B174>0,1,0) -> 0 | G174: =IF(OR(C174>0,D174>0),"1","") | H174: =IF(OR(C174=1,D174=1),1,0) -> 0
A175: Lenhador | F175: =IF(B175>0,1,0) -> 0 | G175: =IF(OR(C175>0,D175>0),"1","") | H175: =IF(OR(C175=1,D175=1),1,0) -> 0
... A194: Meliponicultura | F194: =IF(B194>0,1,0) -> 0 | G194: =IF(OR(C194>0,D194>0),"1","") | H194: =IF(OR(C194=1,D194=1),1,0) -> 0
A195: Mensageiros da Paz | F195: =IF(B195>0,1,0) -> 0
A196: Mergulho | F196: =IF(B196>0,1,0) -> 0 | G196: =IF(OR(C196>0,D196>0),"1","") | H196: =IF(OR(C196=1,D196=1),1,0) -> 0
A197: Meteorologia | F197: =IF(B197>0,1,0) -> 0 | G197: =IF(OR(C197>0,D197>0),"1","") | H197: =IF(OR(C197=1,D197=1),1,0) -> 0
A198: Microbiologia | F198: =IF(B198>0,1,0) -> 0 | G198: =IF(OR(C198>0,D198>0),"1","") | H198: =IF(OR(C198=1,D198=1),1,0) -> 0
A199: Mineralogia | F199: =IF(B199>0,1,0) -> 0 | G199: =IF(OR(C199>0,D199>0),"1","") | H199: =IF(OR(C199=1,D199=1),1,0) -> 0
A200: Minhocultura | F200: =IF(B200>0,1,0) -> 0 | G200: =IF(OR(C200>0,D200>0),"1","") | H200: =IF(OR(C200=1,D200=1),1,0) -> 0
A201: Missionário Católico | F201: =IF(B201>0,1,0) -> 0 | G201: =IF(OR(C201>0,D201>0),"1","") | H201: =IF(OR(C201=1,D201=1),1,0) -> 0
A202: Mitologia | F202: =IF(B202>0,1,0) -> 0 | G202: =IF(OR(C202>0,D202>0),"1","") | H202: =IF(OR(C202=1,D202=1),1,0) -> 0
A203: Montanhismo | F203: =IF(B203>0,1,0) -> 0 | G203: =IF(OR(C203>0,D203>0),"1","") | H203: =IF(OR(C203=1,D203=1),1,0) -> 0
A204: Mountain Bike | F204: =IF(B204>0,1,0) -> 0 | G204: =IF(OR(C204>0,D204>0),"1","") | H204: =IF(OR(C204=1,D204=1),1,0) -> 0
A205: Multimídia | F205: =IF(B205>0,1,0) -> 0 | G205: =IF(OR(C205>0,D205>0),"1","") | H205: =IF(OR(C205=1,D205=1),1,0) -> 0
A206: Musculação | F206: =IF(B206>0,1,0) -> 0 | G206: =IF(OR(C206>0,D206>0),"1","") | H206: =IF(OR(C206=1,D206=1),1,0) -> 0
A207: Museologia | F207: =IF(B207>0,1,0) -> 0 | G207: =IF(OR(C207>0,D207>0),"1","") | H207: =IF(OR(C207=1,D207=1),1,0) -> 0
... A312: Zoologia | F312: =IF(B312>0,1,0) -> 0 | G312: =IF(OR(C312>0,D312>0),"1","") | H312: =IF(OR(C312=1,D312=1),1,0) -> 0
A313: soma para célula I10 - especialidades para a vida | H313: =SUM(H7:H312) -> 0

Sheet Habilidades para a Vida
C1: HABILIDADES PARA A VIDA
C3: APRENDIZAGEM CONTINUA E DESENVOLVIMENTO VOCACIONAL | H3: Soma blocos concluídos | I3: =I7+I78+I117+I164 -> 0
C4: Atividades do Programa Anterior que podem complementar as atividades variáveis:
C5: Atividades Pistas e Trilha Intelectual: I22, I23, I24, I25, I26, I32, I33 Atividades Rumo e Travessia Intelectual: I21, I22, I23, I24
C7: Intencionalidade Educativa | H7: BLOCO CONCLUÍDO ? | I7: =IF(B8="Bloco concluído",1,0) -> 0
B8: =IF(AND(A11="Atingiu 100% das ações fixas",A16="Atingiu 100% das ações variáveis"),"BLOCO CONCLUÍDO","") | C8: Explorar temas que despertam seu interesse, buscar informações confiáveis para aprender mais e experimentar novas ideias e recursos, aplicando esse conhecimento em atividades e projetos de serviço.
C10: Ações Educativas Fixas
A11: =IF(J13>=2,"Atingiu 100% das ações fixas","") | B11: =IF(J11>0,"Item OK","") | C11: Conquistar, no Ramo Escoteiro, uma especialidade sobre um tema de seu interesse e que seja um conhecimento novo. | D11: Alterar manualmente | E11: 0 | H11: Qualquer especialidade | I11: ='Especialidades ou Insígnias'!H313 -> 0 | J11: =IF(E11+I11>=1,1,0) -> 0
B12: =IF(J12>0,"Item OK","") | C12: Em conjunto com a sua patrulha, realizar um Percurso de Gilwell de pelo menos 3km. | D12: Alterar manualmente | F12: Pista 21 | G12: ='Pistas e Trilha'!A41 -> 0 | H12: Pista 22 | I12: ='Pistas e Trilha'!A42 -> 0 | J12: =IF(G12+I12>=2,1,0)+E12 -> 0
I13: soma | J13: =SUM(J11:J12) -> 0
C14: Ações Educativas Variáveis
C15: Realizar QUATRO ações dentre as listadas a seguir:
A16: =IF(OR(J71>0,J66>=4),"Atingiu 100% das ações variáveis","") | B16: =IF(J18>0,"Item OK","") | C16: Enviar e receber mensagens simples em Alfabeto Fonético,Código Internacional de Sinais, Semáfora, Heliografia, Cifra de César ou Criptografia. | D16: Alterar manualmente | F16: Pista 37 | G16: ='Pistas e Trilha'!A67 -> 0 | H16: Rumo 42 | I16: ='Rumo e Travessia'!A70 -> 0
F17: Esp. Entrega de Mensagens | G17: ='Especialidades ou Insígnias'!H102 -> 0
I18: soma | J18: =IF(G16+G17+I16+I17>=1,1,0)+E16 -> 0
B19: =IF(J19>0,"Item OK","") | C19: Visitar com a sua patrulha: hospital, quartel de bombeiros, delegacia, empresas, comércios locais ou outros para conhecer o funcionamento de diferentes profissões | D19: Alterar manualmente | F19: Pista 82 e 83 (ver Guia Aventura Escoteira, pág. 204) | G19: ='Pistas e Trilha'!A146 -> 0 | J19: =IF(G19+I19>=1,1,0)+E19 -> 0
B20: =IF(J22>0,"Item OK","") | C20: Conhecer o funcionamento de serviços de internet, rádio e TV e usar esses conhecimentos para resolver problemas técnicos. | D20: Alterar manualmente | F20: Esp Internet | G20: ='Especialidades ou Insígnias'!H164 -> 0 | H20: Rumo 41 | I20: ='Rumo e Travessia'!A69 -> 0 | J20: =IF(G20+I20>=1,1,0) -> 0
F21: Esp Radioamadorismo | G21: ='Especialidades ou Insígnias'!H253 -> 0 | J21: =IF(G21+I21>=1,1,0) -> 0
I22: soma | J22: =IF(G20+G21+I20+I21>=1,1,0)+E20 -> 0
B23: =IF(J25>0,"Item OK","") | C23: Convidar um especialista da comunidade para dialogar com a tropa e esclarecer dúvidas sobre determinado tema ou profissão | D23: Alterar manualmente | F23: Pista 70 | G23: ='Pistas e Trilha'!A124 -> 0 | H23: Rumo 21 a 24 | I23: ='Rumo e Travessia'!A38 -> 0 | J23: =IF(G23+I23>=1,1,0)+E23 -> 0
F24: Pista 33 | G24: ='Pistas e Trilha'!A59 -> 0
I25: soma | J25: =IF(G23+G24+I23>=1,1,0)+E23 -> 0
B26: =IF(J26>0,"Item OK","") | C26: Utilizar corretamente um radiocomunicador em atividade da patrulha | D26: Alterar manualmente | F26: Pista 38 | G26: ='Pistas e Trilha'!A68 -> 0 | J26: =IF(G26+I26>=1,1,0)+E26 -> 0
B27: =IF(J27>0,"Item OK","") | C27: Realizar uma pesquisa sobre um tema escolhido e apresentar os resultados para a patrulha ou tropa em formato criativo (cartaz, teatro, vídeo, oficina) | D27: Alterar manualmente | F27: Pista 61 | G27: ='Pistas e Trilha'!A109 -> 0 | H27: Rumo 27 | I27: ='Rumo e Travessia'!A47 -> 0 | J27: =IF(G27+I27>=1,1,0)+E27 -> 0
B28: =IF(J28>0,"Item OK","") | C28: Planejar e executar, em conjunto com a sua patrulha, uma ação de serviço comunitário baseada em informações pesquisadas sobre necessidades locais | D28: Alterar manualmente | H28: Rumo 91 | I28: ='Rumo e Travessia'!A154 -> 0 | J28: =IF(G28+I28>=1,1,0)+E28 -> 0
C29: Especialidades que podem complementar as Ações Educativas Variáveis
B30: =IF(J30>0,"Item OK","") | C30: Aeronáutica
B31: =IF(J31>0,"Item OK","") | C31: Arquitetura e Urbanismo | J31: ='Especialidades ou Insígnias'!H22 -> 0
B32: =IF(J32>0,"Item OK","") | C32: Astronomia | J32: ='Especialidades ou Insígnias'!H32 -> 0
B33: =IF(J33>0,"Item OK","") | C33: Biblioteconomia | J33: ='Especialidades ou Insígnias'!H38 -> 0
B34: =IF(J34>0,"Item OK","") | C34: Cartografia | J34: ='Especialidades ou Insígnias'!H50 -> 0
B35: =IF(J35>0,"Item OK","") | C35: Comunicações | J35: ='Especialidades ou Insígnias'!H62 -> 0
B36: =IF(J36>0,"Item OK","") | C36: Confeitaria | J36: ='Especialidades ou Insígnias'!H63 -> 0
B37: =IF(J37>0,"Item OK","") | C37: Construção Civil | J37: ='Especialidades ou Insígnias'!H64 -> 0
B38: =IF(J38>0,"Item OK","") | C38: Criptografia | J38: ='Especialidades ou Insígnias'!H71 -> 0
B39: =IF(J39>0,"Item OK","") | C39: Culinária | J39: ='Especialidades ou Insígnias'!H75 -> 0
B40: =IF(J40>0,"Item OK","") | C40: Design de Interiores | J40: ='Especialidades ou Insígnias'!H85 -> 0
B41: =IF(J41>0,"Item OK","") | C41: E-Sports | J41: ='Especialidades ou Insígnias'!H108 -> 0
B42: =IF(J42>0,"Item OK","") | C42: Etiqueta | J42: ='Especialidades ou Insígnias'!H112 -> 0
B43: =IF(J43>0,"Item OK","") | C43: Fiscalização de Pátio de Aeródromo | J43: ='Especialidades ou Insígnias'!H118 -> 0
C44: GPS | J44: ='Especialidades ou Insígnias'!H133 -> 0
B45: =IF(J45>0,"Item OK","") | C45: Informática | J45: ='Especialidades ou Insígnias'!H154 -> 0
B46: =IF(J46>0,"Item OK","") | C46: Jornalismo | J46: ='Especialidades ou Insígnias'!H172 -> 0
B47: =IF(J47>0,"Item OK","") | C47: Manicure | J47: ='Especialidades ou Insígnias'!H184 -> 0
B48: =IF(J48>0,"Item OK","") | C48: Manutenção Elétrica | J48: ='Especialidades ou Insígnias'!H185 -> 0
B49: =IF(J49>0,"Item OK","") | C49: Marcenaria | J49: ='Especialidades ou Insígnias'!H188 -> 0
B50: =IF(J50>0,"Item OK","") | C50: Marinharia | J50: ='Especialidades ou Insígnias'!H189 -> 0
B51: =IF(J51>0,"Item OK","") | C51: Matemática | J51: ='Especialidades ou Insígnias'!H190 -> 0
B52: =IF(J52>0,"Item OK","") | C52: Mecânica de Automóveis | J52: ='Especialidades ou Insígnias'!H192 -> 0
B53: =IF(J53>0,"Item OK","") | C53: Planador | J53: ='Especialidades ou Insígnias'!H231 -> 0
B54: =IF(J54>0,"Item OK","") | C54: Prevenção de Incêndio | J54: ='Especialidades ou Insígnias'!H241 -> 0
B55: =IF(J55>0,"Item OK","") | C55: Produção Gráfica | J55: ='Especialidades ou Insígnias'!H245 -> 0
B56: =IF(J56>0,"Item OK","") | C56: Programação | J56: ='Especialidades ou Insígnias'!H247 -> 0
B57: =IF(J57>0,"Item OK","") | C57: Química | J57: ='Especialidades ou Insígnias'!H252 -> 0
B58: =IF(J58>0,"Item OK","") | C58: Radioamadorismo | J58: ='Especialidades ou Insígnias'!H253 -> 0
B59: =IF(J59>0,"Item OK","") | C59: Radioescuta | J59: ='Especialidades ou Insígnias'!H254 -> 0
B60: =IF(J60>0,"Item OK","") | C60: Redes de Computadores | J60: ='Especialidades ou Insígnias'!H256 -> 0
B61: =IF(J61>0,"Item OK","") | C61: Segurança no Trânsito | J61: ='Especialidades ou Insígnias'!H274 -> 0
B62: =IF(J62>0,"Item OK","") | C62: Simulação Aérea | J62: ='Especialidades ou Insígnias'!H269 -> 0
B63: =IF(J63>0,"Item OK","") | C63: Sinalização | J63: ='Especialidades ou Insígnias'!H278 -> 0
B64: =IF(J64>0,"Item OK","") | C64: Vendas | J64: ='Especialidades ou Insígnias'!H302 -> 0
B65: =IF(J65>0,"Item OK","") | C65: Web Design | J65: ='Especialidades ou Insígnias'!H308 -> 0
I66: soma | J66: =SUM(J22:J65)+J19+J18 -> 0
C67: OU Conquistar as seguintes insígnias/especialidades:
B68: =IF(J68>0,"Item OK","") | C68: Insígnia do Aprender | J68: ='Especialidades ou Insígnias'!B160 -> 0
B69: =IF(J69>0,"Item OK","") | C69: Insígnia da Modalidade do Mar - Grumete | J69: ='Especialidades ou Insígnias'!B159 -> 0
B70: =IF(J70>0,"Item OK","") | C70: Insígnia da Modalidade do Ar - Aviador | J70: ='Especialidades ou Insígnias'!B158 -> 0
I71: soma | J71: =SUM(J68:J70) -> 0
C74: AUTONOMIA E LIDERANÇA
C75: Atividades do Programa Anterior que podem complementar as atividades variáveis:
C76: Atividades Pistas e Trilha Intelectual: I28, I29, I30, I31 Social: S73, S74, S75, S76 Atividades Rumo e Travessia Intelectual: I25, I26, I27, I28 Caráter: C51, C52, C53, C54
C78: Intencionalidade Educativa | H78: BLOCO CONCLUÍDO ? | I78: =IF(B79="Bloco concluído",1,0) -> 0
B79: =IF(AND(A83="Atingiu 100% das ações fixas",A87="Atingiu 100% das ações variáveis"),"BLOCO CONCLUÍDO","") | C79: Assumir diferentes papéis em sua patrulha, sabendo quando colaborar e quando liderar. Aprender a administrar seu dinheiro para realizar atividades e projetos, além de planejar e avaliar tarefas junto com o grupo, tomando decisões de forma responsável.
D80: soma | E80: =SUM(E78:E79) -> 0
C82: Ações Educativas Fixas
A83: =IF(J83>=1,"Atingiu 100% das ações fixas","") | B83: =IF(J83>0,"Item OK","") | C83: Montar corretamente uma mochila para um acampamento, mantendo o equipamento em bom estado | D83: Alterar manualmente | F83: pistas 11 | G83: ='Pistas e Trilha'!A22 -> 0 | H83: rumo 11 | I83: ='Rumo e Travessia'!A20 -> 0 | J83: =IF(G83+I83>=1,1,0)+E83 -> 0
C85: Ações Educativas Variáveis
C86: Realizar CINCO ações dentre as listadas a seguir:
A87: =IF(J110>=5,"Atingiu 100% das ações variáveis","") | B87: =IF(J87>0,"Item OK","") | C87: Contribuir para o planejamento e a organização de uma excursão de patrulha. | D87: Alterar manualmente | F87: pista 30 | G87: ='Pistas e Trilha'!A54 -> 0 | J87: =IF(G87+I87>=1,1,0)+E87 -> 0
B88: =IF(J88>0,"Item OK","") | C88: Fazer uma excursão urbana com a sua patrulha ou tropa, se locomovendo por meio de transportes públicos como ônibus, trens, metrô, entre outros. | D88: Alterar manualmente | F88: pista 96 | G88: ='Pistas e Trilha'!A169 -> 0 | J88: =IF(G88+I88>=1,1,0)+E88 -> 0
B89: =IF(J89>0,"Item OK","") | C89: Pesquisar e realizar as compras dos alimentos para um acampamento, apresentando para a patrulha uma prestação de contas. | D89: Alterar manualmente | H89: Rumo 12 a 14 | I89: ='Rumo e Travessia'!A22 -> 0 | J89: =IF(G89+I89>=1,1,0)+E89 -> 0
B90: =IF(J90>0,"Item OK","") | C90: Saber onde encontrar, identificando em um mapa, os principais serviços públicos na cidade. | D90: Alterar manualmente | F90: pista 82 | G90: ='Pistas e Trilha'!A147 -> 0 | H90: pista 83 | I90: ='Pistas e Trilha'!A148 -> 0 | J90: =IF(G90+I90>=1,1,0)+E90 -> 0
B91: =IF(J91>0,"Item OK","") | C91: Planejar e executar em patrulha um projeto de captação de recursos para participação em uma atividade escoteira. | D91: Alterar manualmente | F91: pista 74 | G91: ='Pistas e Trilha'!A133 -> 0 | J91: =IF(G91+I91>=1,1,0)+E91 -> 0
B92: =IF(J92>0,"Item OK","") | C92: Participar de atividades ou oficinas sobre finanças pessoais. | D92: Alterar manualmente | F92: Esp Educação Financeira | G92: ='Especialidades ou Insígnias'!H93 -> 0 | J92: =IF(G92+I92>=1,1,0)+E92 -> 0
B93: =IF(J96>0,"Item OK","") | C93: Assumir pelo menos três encargos diferentes na patrulha, sendo bem avaliado pelos seus companheiros. | D93: Alterar manualmente | F93: pista 45 | G93: ='Pistas e Trilha'!A80 -> 0 | H93: rumo 51 | I93: ='Rumo e Travessia'!A86 -> 0 | J93: =IF(G93+I93>=1,1,0) -> 0
F94: pista 52 a 54 | G94: ='Pistas e Trilha'!A94 -> 0 | H94: rumo 52 | I94: ='Rumo e Travessia'!A87 -> 0 | J94: =IF(G94+I94>=1,1,0) -> 0
F95: pista 75 | G95: ='Pistas e Trilha'!A134 -> 0 | H95: rumo 53 | I95: ='Rumo e Travessia'!A88 -> 0 | J95: =IF(G95+I95>=1,1,0) -> 0
I96: soma | J96: =IF(G93+I93+G94+G95+I94+I95>=1,1,0)+E93 -> 0
B97: =IF(J99>0,"Item OK","") | C97: Administrar o fundo de patrulha por pelo menos três meses, registrando receitas e despesas, e utilizar os recursos em atividades planejadas pela patrulha. | D97: Alterar manualmente | F97: Pista 75 | G97: ='Pistas e Trilha'!A134 -> 0 | H97: Rumo 51 | I97: ='Rumo e Travessia'!A86 -> 0 | J97: =IF(G97+I97>=1,1,0)+E97 -> 0
F98: Pista 76 | G98: ='Pistas e Trilha'!A135 -> 0
I99: soma | J99: =IF(G97+G98+I97>=1,1,0)+E97 -> 0
B100: =IF(J100>0,"Item OK","") | C100: Registrar receitas e despesas simples ou da mesada em planilha ou caderno por um período determinado. | D100: Alterar manualmente | J100: =IF(G100+I100>=1,1,0)+E100 -> 0
B101: =IF(J103>0,"Item OK","") | C101: Conduzir uma reunião de patrulha como monitor ou secretário, registrando decisões e acompanhando sua execução. | D101: Alterar manualmente | F101: Pista 29 | G101: ='Pistas e Trilha'!A53 -> 0 | H101: Rumo 67 | I101: ='Rumo e Travessia'!A113 -> 0
F102: Pista 60 | G102: ='Pistas e Trilha'!A108 -> 0 | J102: =IF(G102+I102>=1,1,0) -> 0
I103: soma | J103: =IF(G101+G102+I101+I102>=1,1,0)+E101 -> 0
C104: Conquistar ao menos uma das seguintes especialidades a seguir no nível 2
B105: =IF(J105>0,"Item OK","") | C105: Administração | J105: ='Especialidades ou Insígnias'!H9 -> 0
B106: =IF(J106>0,"Item OK","") | C106: Educação Financeira | J106: ='Especialidades ou Insígnias'!H93 -> 0
B107: =IF(J107>0,"Item OK","") | C107: Empreendedorismo | J107: ='Especialidades ou Insígnias'!H96 -> 0
B108: =IF(J108>0,"Item OK","") | C108: Oratória | J108: ='Especialidades ou Insígnias'!H216 -> 0
...

Sheet Meio Ambiente
C1: MEIO AMBIENTE
C3: CONSUMO RESPONSÁVEL | H3: Soma blocos concluídos | I3: =I7+I45+I71+I111 -> 0
C4: Atividades do Programa Anterior que podem complementar as atividades variáveis:
C5: Atividades Rumo e Travessia Intelectual: I39, I40
C7: Intencionalidade Educativa | H7: BLOCO CONCLUÍDO ? | I7: =IF(B8="Bloco concluído",1,0) -> 0
B8: =IF(AND(A11="Atingiu 100% das ações fixas",A17="Atingiu 100% das ações variáveis"),"BLOCO CONCLUÍDO","") | C8: Praticar o consumo consciente diariamente, evitando desperdícios e ajudando a preservar os recursos naturais
C10: Ações Educativas Fixas
A11: =IF(J13>=2,"Atingiu 100% das ações fixas","") | B11: =IF(J11>0,"Item OK","") | C11: Em acampamentos e excursões, criar soluções para melhorar a higiene e conforto e classificar os resíduos em categorias, tratando-os adequadamente. | D11: Alterar manualmente | F11: pista 8 | G11: ='Pistas e Trilha'!A19 -> 0 | J11: =IF(G11+I11>=1,1,0)+E11 -> 0
B12: =IF(J12>0,"Item OK","") | C12: Planejar adequadamente e adquirir as quantidades dos alimentos para refeições em um acampamento para sua patrulha, evitando desperdício. | D12: Alterar manualmente | H12: rumo 13 | I12: ='Rumo e Travessia'!A24 -> 0 | J12: =IF(G12+I12>=1,1,0)+E12 -> 0
I13: soma | J13: =SUM(J11:J12) -> 0
C15: Ações Educativas Variáveis
C16: Realizar CINCO ações dentre as listadas a seguir:
A17: =IF(OR(H39>0,H35>=5),"Atingiu 100% das ações variáveis","") | B17: =IF(J17>0,"Item OK","") | C17: Registrar e analisar o consumo de água e energia da sua residência, buscando ideias para economizar, e apresentar para sua patrulha os resultados. | D17: Alterar manualmente | F17: Esp Energia n3 | G17: ='Especialidades ou Insígnias'!H98 -> 0 | J17: =IF(G17+I17>=1,1,0)+E17 -> 0
B18: =IF(J18>0,"Item OK","") | C18: Avaliar o impacto ambiental de uma atividade e apresentar alternativas mais sustentáveis. | D18: Alterar manualmente | F18: pista 1 | G18: ='Pistas e Trilha'!A8 -> 0 | H18: rumo 1 | I18: ='Rumo e Travessia'!A6 -> 0 | J18: =IF(G18+I18>=1,1,0)+E18 -> 0
B19: =IF(J19>0,"Item OK","") | C19: Visitar uma estação de energia renovável, uma estação de tratamento de água, uma cooperativa ou usina de reciclagem ou outras opções semelhantes. | D19: Alterar manualmente | F19: Esp Energia n3 | G19: ='Especialidades ou Insígnias'!H98 -> 0 | J19: =IF(G19+I19>=1,1,0)+E19 -> 0
B20: =IF(J20>0,"Item OK","") | C20: Consertar objetos simples, como brinquedos ou pequenos eletrodomésticos. | D20: Alterar manualmente | F20: Esp Reparos Domésticos n3 | G20: ='Especialidades ou Insígnias'!H260 -> 0 | J20: =IF(G20+I20>=1,1,0)+E20 -> 0
B21: =IF(J21>0,"Item OK","") | C21: Utilizar embalagens retornáveis ou reutilizáveis nas refeições de campo, evitando descartáveis. | D21: Alterar manualmente | F21: Pista 94 | G21: ='Pistas e Trilha'!A167 -> 0 | H21: rumo 1 | I21: ='Rumo e Travessia'!A6 -> 0 | J21: =IF(G21+I21>=1,1,0)+E21 -> 0
F22: Pista 1 | G22: ='Pistas e Trilha'!A8 -> 0
I23: soma | J23: =IF(G21+G22+I21+I22>=2,1,0)+E21 -> 0
B24: =IF(J24>0,"Item OK","") | C24: Separar resíduos orgânicos e criar um sistema de compostagem caseira | D24: Alterar manualmente | F24: Esp Compostagem | G24: ='Especialidades ou Insígnias'!H61 -> 0 | J24: =IF(G24+I24>=1,1,0)+E24 -> 0
B25: =IF(J25>0,"Item OK","") | C25: Criar uma campanha educativa para a tropa sobre consumo consciente e economia de recursos. | D25: Alterar manualmente | J25: =IF(G25+I25>=1,1,0)+E25 -> 0
B26: =IF(J26>0,"Item OK","") | C26: Trocar roupas, livros ou jogos com amigos e familiares em vez de comprar novos. | D26: Alterar manualmente | J26: =IF(G26+I26>=1,1,0)+E26 -> 0
B27: =IF(J27>0,"Item OK","") | C27: Organizar, com sua patrulha, uma campanha de conscientização sobre consumo responsável. | D27: Alterar manualmente | J27: =IF(G27+I27>=1,1,0)+E27 -> 0
B28: =IF(J28>0,"Item OK","") | C28: Confeccionar utensílios ou equipamentos a partir de materiais reciclados para uso nas atividades da patrulha. | D28: Alterar manualmente | J28: =IF(G28+I28>=1,1,0)+E28 -> 0
B29: =IF(J29>0,"Item OK","") | C29: Planejar e realizar as refeições de um dia de acampamento sem carne, garantindo a ingestão adequada de proteínas. | D29: Alterar manualmente | J29: =IF(G29+I29>=1,1,0)+E29 -> 0
B30: =IF(J30>0,"Item OK","") | C30: Organizar, cuidar e fazer reparos nos materiais da patrulha. | D30: Alterar manualmente | J30: =IF(G30+I30>=1,1,0)+E30 -> 0
C31: Especialidades que podem complementar as Ações Educativas Variáveis
B32: =IF(H32>0,"Item OK","") | C32: Agricultura | H32: ='Especialidades ou Insígnias'!H11 -> 0
B33: =IF(H33>0,"Item OK","") | C33: Aquicultura | H33: ='Especialidades ou Insígnias'!H19 -> 0
B34: =IF(H34>0,"Item OK","") | C34: Energia | H34: ='Especialidades ou Insígnias'!H98 -> 0
G35: soma | H35: =SUM(J17:J30)-J21-J22+H32+H33+H34 -> 0
C36: Conquistar ao menos uma das seguintes especialidades a seguir no nível 2 ou Insígnias
B37: =IF(H37>0,"Item OK","") | C37: Horticultura | H37: ='Especialidades ou Insígnias'!H149 -> 0
B38: =IF(H38>0,"Item OK","") | C38: Reduzir, Reciclar e Reutilizar | H38: ='Especialidades ou Insígnias'!B163 -> 0
G39: soma | H39: =SUM(H37:H38) -> 0
C41: MUDANÇAS CLIMÁTICAS
C42: Atividades do Programa Anterior que podem complementar as atividades variáveis:
C43: Atividades Pistas e Trilha Intelectual: I27 Atividades Rumo e Travessia Social: S100, S101, S102
C45: Intencionalidade Educativa | H45: BLOCO CONCLUÍDO ? | I45: =IF(B46="Bloco concluído",1,0) -> 0
B46: =IF(A50="Atingiu 100% das ações variáveis","BLOCO CONCLUÍDO","") | C46: Se envolver em atividades e projetos para reduzir os impactos ambientais e combater as mudanças climáticas.
C48: Ações Educativas Variáveis
C49: Realizar CINCO ações dentre as listadas a seguir:
A50: =IF(OR(H65>0,H62>=3),"Atingiu 100% das ações variáveis","") | B50: =IF(J50>0,"Item OK","") | C50: Em um acampamento, criar uma estação meteorológica simples para registrar temperatura, umidade, direção do vento, nuvens e possíveis mudanças no tempo. | D50: Alterar manualmente | F50: Esp Metereologia | G50: ='Especialidades ou Insígnias'!H197 -> 0 | J50: =IF(G50+I50>=1,1,0)+E50 -> 0
B51: =IF(J51>0,"Item OK","") | C51: Participar da construção de um fogão solar e usá-lo em um acampamento de patrulha ou tropa. | D51: Alterar manualmente | H51: rumo 39 | I51: ='Rumo e Travessia'!A67 -> 0 | J51: =IF(G51+I51>=1,1,0)+E51 -> 0
B52: =IF(J52>0,"Item OK","") | C52: Participar de uma excursão urbana com foco ecológico, identificando situações de risco para a sociedade referentes às mudanças climáticas. | D52: Alterar manualmente | F52: pista 96 | G52: ='Pistas e Trilha'!A169 -> 0 | J52: =IF(G52+I52>=1,1,0)+E52 -> 0
B53: =IF(J53>0,"Item OK","") | C53: Visitar ou participar de uma atividade com uma organização que atua em prol do meio ambiente. | D53: Alterar manualmente | H53: rumo 100 | I53: ='Rumo e Travessia'!A175 -> 0 | J53: =IF(G53+I53>=1,1,0)+E53 -> 0
B54: =IF(J54>0,"Item OK","") | C54: Em uma excursão ou acampamento em área não urbana, identificar ações prejudiciais à natureza, como extrativismo e mineração, e listar seus impactos. | D54: Alterar manualmente | J54: =IF(G54+I54>=1,1,0)+E54 -> 0
B55: =IF(J55>0,"Item OK","") | C55: Planejar e participar de uma excursão, utilizando meios de transporte que dependem de fontes de energia limpa (bicicleta, ônibus elétrico, embarcação a remo, entre outros). | D55: Alterar manualmente | H55: rumo 101 | I55: ='Rumo e Travessia'!A176 -> 0 | J55: =IF(G55+I55>=1,1,0)+E55 -> 0
B56: =IF(J56>0,"Item OK","") | C56: Organizar, com sua patrulha ou tropa, um projeto de conscientização sobre o uso de energia e água em sua escola, condomínio ou sede da UEL. | D56: Alterar manualmente | F56: pista 94 a 96 | G56: ='Pistas e Trilha'!A166 -> 0 | J56: =IF(G56+I56>=1,1,0)+E56 -> 0
B57: =IF(J57>0,"Item OK","") | C57: Participar de mutirões de plantio de mudas ou cultivo de uma horta em casa, na escola ou na UEL. | D57: Alterar manualmente | J57: =IF(G57+I57>=1,1,0)+E57 -> 0
C58: Especialidades que podem complementar as Ações Educativas Variáveis
B59: =IF(H59>0,"Item OK","") | C59: Agricultura | H59: ='Especialidades ou Insígnias'!H11 -> 0
B60: =IF(H60>0,"Item OK","") | C60: Energia | H60: ='Especialidades ou Insígnias'!H98 -> 0
B61: =IF(H61>0,"Item OK","") | C61: Jardinagem e Paisagismo | H61: ='Especialidades ou Insígnias'!H169 -> 0
C62: Conquistar ao menos uma das seguintes especialidades a seguir no nível 2 ou Insígnias | G62: soma | H62: =SUM(J50:J57)+H59+H60+H61 -> 0
B63: =IF(H63>0,"Item OK","") | C63: Metereologia | H63: ='Especialidades ou Insígnias'!H197 -> 0
B64: =IF(H64>0,"Item OK","") | C64: Escoteiros pela Energia Solar | H64: ='Especialidades ou Insígnias'!B162 -> 0
G65: soma | H65: =SUM(H63:H64) -> 0
C67: PRESERVAÇÃO DA BIODIVERSIDADE
C68: Atividades do Programa Anterior que podem complementar as atividades variáveis:
C69: Atividades Pistas e Trilha Social: S94, S95, S96
C71: Intencionalidade Educativa | H71: BLOCO CONCLUÍDO ? | I71: =IF(B72="Bloco concluído",1,0) -> 0
B72: =IF(AND(A76="Atingiu 100% das ações fixas",A80="Atingiu 100% das ações variáveis"),"BLOCO CONCLUÍDO","") | C72: Cuidar dos animais e das plantas, entendendo como as atitudes humanas podem protegê-los ou prejudicá-los.
C75: Ações Educacionais Fixas
A76: =IF(J76>=1,"Atingiu 100% das ações fixas","") | B76: =IF(J76>0,"Item OK","") | C76: Participar, em patrulha, de uma atividade de exploração em ambiente natural, reconhecendo a fauna e a flora locais e identificando riscos à preservação, além de propor soluções para evitá-los | D76: Alterar manualmente | F76: Pista 94 a 96 | G76: ='Pistas e Trilha'!A166 -> 0 | J76: =IF(G76+I76>=1,1,0)+E76 -> 0
C78: Ações Educacionais Variáveis
C79: Realizar CINCO ações dentre as listadas a seguir:
A80: =IF(OR(H105>0,H99>=5),"Atingiu 100% das ações variáveis","") | B80: =IF(J80>0,"Item OK","") | C80: Reconhecer os animais venenosos e peçonhentos da região e saber como agir em casos de picadas ou contaminação | D80: Alterar manualmente | H80: rumo 4 | I80: ='Rumo e Travessia'!A11 -> 0 | J80: =IF(G80+I80>=1,1,0)+E80 -> 0
B81: =IF(J81>0,"Item OK","") | C81: Planejar e executar um projeto ambiental com a patrulha ou tropa. | D81: Alterar manualmente | H81: rumo 100 a 102 | I81: ='Rumo e Travessia'!A174 -> 0 | J81: =IF(G81+I81>=1,1,0)+E81 -> 0
B82: =IF(J82>0,"Item OK","") | C82: Plantar uma espécie nativa e observar seu crescimento, registrando cada etapa. | D82: Alterar manualmente | F82: Pista 96 | G82: ='Pistas e Trilha'!A169 -> 0 | H82: rumo 101 | I82: ='Rumo e Travessia'!A176 -> 0 | J82: =IF(G82+I82>=1,1,0)+E82 -> 0
B83: =IF(J83>0,"Item OK","") | C83: Identificar as pegadas de pelo menos cinco animais da fauna brasileira e realizar levantamento das pegadas em áreas naturais. | D83: Alterar manualmente | H83: rumo 102 | I83: ='Rumo e Travessia'!A177 -> 0 | J83: =IF(G83+I83>=1,1,0)+E83 -> 0
B84: =IF(J84>0,"Item OK","") | C84: Participar de uma atividade de mergulho que tenha o objetivo de conhecer e explorar a vida na água. | D84: Alterar manualmente | J84: =IF(G84+I84>=1,1,0)+E84 -> 0
B85: =IF(J85>0,"Item OK","") | C85: Participar de uma atividade de observação de animais noturnos com sua patrulha. | D85: Alterar manualmente | J85: =IF(G85+I85>=1,1,0)+E85 -> 0
B86: =IF(J86>0,"Item OK","") | C86: Observar e registrar espécies de aves, insetos, plantas ou outros animais durante um acampamento ou excursão. | D86: Alterar manualmente | J86: =IF(G86+I86>=1,1,0)+E86 -> 0
B87: =IF(J87>0,"Item OK","") | C87: Visitar parques, reservas ou centros de proteção ambiental para conhecer ações de preservação da fauna e da flora. | D87: Alterar manualmente | H87: Rumo 100 | I87: ='Rumo e Travessia'!A175 -> 0 | J87: =IF(G87+I87>=1,1,0)+E87 -> 0
B88: =IF(J88>0,"Item OK","") | C88: Construir comedouros ou bebedouros para aves e instalar em áreas adequadas, acompanhando seu uso. | D88: Alterar manualmente | J88: =IF(G88+I88>=1,1,0)+E88 -> 0
B89: =IF(J89>0,"Item OK","") | C89: Criar materiais educativos, como vídeos ou posts, sobre a importância de preservar a biodiversidade. | D89: Alterar manualmente | J89: =IF(G89+I89>=1,1,0)+E89 -> 0
C90: Especialidades que podem complementar as Ações Educativas Variáveis
B91: =IF(H91>0,"Item OK","") | C91: Animais Venenosos e Peçonhentos | H91: ='Especialidades ou Insígnias'!H16 -> 0
B92: =IF(H92>0,"Item OK","") | C92: Aquarismo | H92: ='Especialidades ou Insígnias'!H18 -> 0
B93: =IF(H93>0,"Item OK","") | C93: Biologia | H93: ='Especialidades ou Insígnias'!H39 -> 0
B94: =IF(H94>0,"Item OK","") | C94: Cuidados Animais de Estimação | H94: ='Especialidades ou Insígnias'!H70 -> 0
B95: =IF(H95>0,"Item OK","") | C95: Entomologia | H95: ='Especialidades ou Insígnias'!H101 -> 0
B96: =IF(H96>0,"Item OK","") | C96: Geologia | H96: ='Especialidades ou Insígnias'!H130 -> 0
B97: =IF(H97>0,"Item OK","") | C97: Melipolicultura | H97: ='Especialidades ou Insígnias'!H194 -> 0
B98: =IF(H98>0,"Item OK","") | C98: Microbiologia | H98: ='Especialidades ou Insígnias'!H198 -> 0
G99: soma | H99: =SUM(J80:J89)+SUM(H91:H98) -> 0
C100: Conquistar ao menos uma das seguintes especialidades a seguir no nível 2 ou Insígnias
B101: =IF(H101>0,"Item OK","") | C101: Zoologia | H101: ='Especialidades ou Insígnias'!H312 -> 0
B102: =IF(H102>0,"Item OK","") | C102: Oceanologia | H102: ='Especialidades ou Insígnias'!H215 -> 0
B103: =IF(H103>0,"Item OK","") | C103: Botânica | H103: ='Especialidades ou Insígnias'!H41 -> 0
B104: =IF(H104>0,"Item OK","") | C104: Campeões da Natureza | H104: ='Especialidades ou Insígnias'!B155 -> 0
G105: soma | H105: =SUM(H101:H104) -> 0
C107: VIDA AO AR LIVRE
C108: Atividades do Programa Anterior que podem complementar as atividades variáveis:
C109: Atividades Pistas e Trilha Físico: F1 Intelectual: I21, I40, I41, I42
C111: Intencionalidade Educativa | H111: BLOCO CONCLUÍDO ? | I111: =IF(B112="Bloco concluído",1,0) -> 0
B112: =IF(AND(A116="Atingiu 100% das ações fixas",A129="Atingiu 100% das ações variáveis"),"BLOCO CONCLUÍDO","") | C112: Aproveitar as atividades ao ar livre com responsabilidade, respeitando a natureza e deixando os lugares sempre melhores do que encontrou.
C115: Ações Educativas Fixas
A116: =IF(J126>=8,"Atingiu 100% das ações fixas","") | B116: =IF(J116>0,"Item OK","") | C116: Montar o campo de patrulha com pioneirias como mesa, pórtico e canto do lenhador, utilizando amarras adequadas. | D116: Alterar manualmente | F116: rumo 43 | G116: ='Rumo e Travessia'!A73 -> 0 | J116: =IF(G116+I116>=1,1,0)+E116 -> 0
...

Sheet Paz e Desenvolvimento
C1: PAZ E DESENVOLVIMENTO
C3: COMUNIDADE | F3: Soma blocos concluídos | G3: =G7+G33+G57+G111+G147 -> 0
C4: Atividades do Programa Anterior que podem complementar as atividades variáveis:
C5: Atividades Pistas e Trilha Social: S80, S81 Atividades Rumo e Travessia Intelectual: I33, I34, I35 Social: S88, S89, S90, S91
C7: Intencionalidade Educativa | F7: BLOCO CONCLUÍDO ? | G7: =IF(B8="Bloco concluído",1,0) -> 0
B8: =IF(AND(A11="Atingiu 100% das ações fixas",A16="Atingiu 100% das ações variáveis"),"BLOCO CONCLUÍDO","") | C8: Realizar boas ações diariamente e trabalhar em equipe para organizar atividades e projetos de serviço que beneficiem a comunidade
C10: Ações Educativas Fixas
A11: =IF(J13>=2,"Atingiu 100% das ações fixas","") | B11: =IF(J11>0,"Item OK","") | C11: Identificar, sozinho ou em patrulha, uma necessidade da comunidade e planejar e executar uma ação comunitária. | D11: Alterar manualmente | H11: rumo 91 | I11: ='Rumo e Travessia'!A154 -> 0 | J11: =IF(G11+I11>=1,1,0)+E11 -> 0
B12: =IF(J12>0,"Item OK","") | C12: Identificar os riscos de desastres naturais na comunidade e conhecer os hospitais e contatos de emergência, sabendo quando acionar cada um. | D12: Alterar manualmente | H12: rumo 4 a 7 | I12: ='Rumo e Travessia'!A10 -> 0 | J12: =IF(G12+I12>=1,1,0)+E12 -> 0
I13: soma | J13: =SUM(J11:J12) -> 0
C14: Ações Educativas Variáveis
C15: Realizar TRÊS ações dentre as listadas a seguir:
A16: =IF(OR(J27>0,J23>=3),"Atingiu 100% das ações variáveis","") | B16: =IF(J16>0,"Item OK","") | C16: Aplicar o conhecimento adquirido nas especialidades em ações de serviço à comunidade. | D16: Alterar manualmente | H16: rumo 33 | I16: ='Rumo e Travessia'!A52 -> 0 | J16: =IF(G16+I16>=1,1,0)+E16 -> 0
B17: =IF(J17>0,"Item OK","") | C17: Participar ativamente de pelo menos uma campanha de serviço e desenvolvimento comunitário organizadas pela UEL, distrito ou região. | D17: Alterar manualmente | F17: pista 80 e 81 | G17: ='Pistas e Trilha'!A142 -> 0 | H17: rumo 70 | I17: ='Rumo e Travessia'!A118 -> 0 | J17: =IF(G17+I17>=1,1,0)+E17 -> 0
B18: =IF(J18>0,"Item OK","") | C18: Organizar uma oficina de brinquedos, doando os itens consertados para uma instituição que atende crianças carentes. | D18: Alterar manualmente | H18: rumo 60 | I18: ='Rumo e Travessia'!A101 -> 0 | J18: =IF(G18+I18>=1,1,0)+E18 -> 0
B19: =IF(J19>0,"Item OK","") | C19: Colaborar em ações organizadas por outras instituições de serviço. | D19: Alterar manualmente | F19: pista 80 e 81 | G19: ='Pistas e Trilha'!A152 -> 0 | H19: rumo 70 | I19: ='Rumo e Travessia'!A118 -> 0 | J19: =IF(G19+I19>=1,1,0)+E19 -> 0
C20: Especialidades que podem complementar as Ações Educativas Variáveis
B21: =IF(J21>0,"Item OK","") | C21: Inclusão | J21: ='Especialidades ou Insígnias'!H152 -> 0
B22: =IF(J22>0,"Item OK","") | C22: Libras | J22: ='Especialidades ou Insígnias'!H176 -> 0
C23: OU conquistar ao menos uma das seguintes especialidades a seguir no nível 2 ou Insígnias | I23: soma | J23: =SUM(J16:J22) -> 0
B24: =IF(J24>0,"Item OK","") | C24: Defesa Civil | J24: ='Especialidades ou Insígnias'!H83 -> 0
B25: =IF(J25>0,"Item OK","") | C25: Mensageiros da Paz | J25: ='Especialidades ou Insígnias'!H195 -> 0
B26: =IF(J26>0,"Item OK","") | C26: Insíginia da Ação Comunitária | J26: ='Especialidades ou Insígnias'!B156 -> 0
I27: soma | J27: =SUM(J24:J26) -> 0
C29: DEMOCRACIA
C30: Atividades do Programa Anterior que podem complementar as atividades variáveis:
C31: Atividades Pistas e Trilha Afetivo A59, A60, A61, A62 Social: S77, S78, S79 Atividades Rumo e Travessia Social: S81, S82, S83, S84, S85, S86, S87
C33: Intencionalidade Educativa | F33: BLOCO CONCLUÍDO ? | G33: =IF(B34="Bloco concluído",1,0) -> 0
B34: =IF(AND(A37="Atingiu 100% das ações fixas",A43="Atingiu 100% das ações variáveis"),"BLOCO CONCLUÍDO","") | C34: Participar das decisões da tropa, contribuindo com suas ideias, respeitando as opiniões dos colegas e se comprometendo a seguir o que foi decidido coletivamente.
C36: Ações Educativas Fixas
A37: =IF(J40>=3,"Atingiu 100% das ações fixas","") | B37: =IF(J37>0,"Item OK","") | C37: Participar ativamente das decisões do Conselho de Patrulha, contribuindo com ideias, votando e assumindo responsabilidades, respeitando os resultados | D37: Alterar manualmente | H37: rumo 67 | I37: ='Rumo e Travessia'!A113 -> 0 | J37: =IF(G37+I37>=1,1,0)+E37 -> 0
B38: =IF(J38>0,"Item OK","") | C38: Participar ativamente das decisões da Assembleia de Tropa, contribuindo com ideias, votando e assumindo responsabilidades, respeitando os resultados | D38: Alterar manualmente | F38: pista 59 a 62 | G38: ='Pistas e Trilha'!A106 -> 0 | J38: =IF(G38+I38>=1,1,0)+E38 -> 0
B39: =IF(J39>0,"Item OK","") | C39: Participar da eleição de monitor da patrulha e das decisões de encargos, respeitando os resultados | D39: Alterar manualmente | F39: pista 52 a 54 | G39: ='Pistas e Trilha'!A94 -> 0 | J39: =IF(G39+I39>=1,1,0)+E39 -> 0
I40: soma | J40: =SUM(J37:J39) -> 0
C41: Ações Educativas Variáveis
C42: Realizar DUAS ações dentre as listadas a seguir:
A43: =IF(J51>=2,"Atingiu 100% das ações variáveis","") | B43: =IF(J43>0,"Item OK","") | C43: Visitar a sede administrativa de qualquer um dos três poderes, e explicar a importância e as particularidades desta forma de governo, conhecendo a constituição e os símbolos nacionais, do estado e município. | D43: Alterar manualmente | H43: rumo 82 | I43: ='Rumo e Travessia'!A139 -> 0 | J43: =IF(G43+I43>=1,1,0)+E43 -> 0
B44: =IF(J44>0,"Item OK","") | C44: Conhecer a estrutura do Grupo Escoteiro ou Seção Autônoma e participar de uma Assembleia de Grupo Escoteiro. | D44: Alterar manualmente | F44: pista 79 | G44: ='Pistas e Trilha'!A140 -> 0 | H44: rumo 84 | I44: ='Rumo e Travessia'!A143 -> 0 | J44: =IF(G44+I44>=1,1,0)+E44 -> 0
B45: =IF(J45>0,"Item OK","") | C45: Participar ativamente de um fórum de jovens do grupo escoteiro. | D45: Alterar manualmente | J45: =IF(G45+I45>=1,1,0)+E45 -> 0
B46: =IF(J46>0,"Item OK","") | C46: Aprender e compartilhar sobre a história do voto e da democracia no Brasil. | D46: Alterar manualmente | H46: rumo 81 a 83 | I46: ='Rumo e Travessia'!A137 -> 0 | J46: =IF(G46+I46>=1,1,0)+E46 -> 0
C47: Especialidades que podem complementar as Ações Educativas Variáveis
B48: =IF(J48>0,"Item OK","") | C48: Prevenção às Fake News | J48: ='Especialidades ou Insígnias'!H236 -> 0
B49: =IF(J49>0,"Item OK","") | C49: Geografia | J49: ='Especialidades ou Insígnias'!H129 -> 0
B50: =IF(J50>0,"Item OK","") | C50: Paz e Justiça | J50: ='Especialidades ou Insígnias'!H224 -> 0
I51: soma | J51: =SUM(J43:J50) -> 0
C53: HERANÇA CULTURAL
C54: Atividades do Programa Anterior que podem complementar as atividades variáveis:
C55: Atividades Pistas e Trilha Social: S84, S85, S86, S87
C57: Intencionalidade Educativa | F57: BLOCO CONCLUÍDO ? | G57: =IF(B58="Bloco concluído",1,0) -> 0
B58: =IF(AND(A61="Atingiu 100% das ações fixas",A65="Atingiu 100% das ações variáveis"),"BLOCO CONCLUÍDO","") | C58: Explorar e valorizar a cultura de sua comunidade e de seus país, conhecendo costumes, tradições, folclore e geografia, e propor atividades para compartilhar esses conhecimentos com os outros.
C60: Ações Educativas Fixas
A61: =IF(J61>0,"Atingiu 100% das ações fixas","") | B61: =IF(J61>0,"Item OK","") | C61: Realizar o hasteamento ou arriamento da bandeira em cerimônia de abertura ou encerramento de atividade. | D61: Alterar manualmente | F61: pista 47 | G61: ='Pistas e Trilha'!A84 -> 0 | H61: rumo 81 | I61: ='Rumo e Travessia'!A14 -> 0 | J61: =IF(G61+I61>=1,1,0)+E61 -> 0
C63: Ações Educativas Variáveis
C64: Realizar CINCO ações dentre as listadas a seguir:
A65: =IF(OR(J105>0,J100>=5),"Atingiu 100% das ações variáveis","") | B65: =IF(J65>0,"Item OK","") | C65: Desenvolver sua "Árvore Genealógica”, pesquisando seu sobrenome, significado e a história dos seus antepassados, situando-os no contexto histórico, e apresentá-la para sua patrulha. | D65: Alterar manualmente | F65: Esp Genealogia | G65: ='Especialidades ou Insígnias'!H126 -> 0 | J65: =IF(G65+I65>=1,1,0)+E65 -> 0
B66: =IF(J66>0,"Item OK","") | C66: Participar das cerimônias com os símbolos nacionais e cantar o Hino Nacional corretamente. | D66: Alterar manualmente | F66: pista 47 | G66: ='Pistas e Trilha'!A84 -> 0 | H66: rumo 81 | I66: ='Rumo e Travessia'!A138 -> 0 | J66: =IF(G66+I66>=1,1,0)+E66 -> 0
B67: =IF(J67>0,"Item OK","") | C67: Apresentar para sua patrulha ou tropa histórias de mulheres que se destacaram em nosso país. | D67: Alterar manualmente | F67: pista 67 | G67: ='Pistas e Trilha'!A119 -> 0 | J67: =IF(G67+I67>=1,1,0)+E67 -> 0
B68: =IF(J68>0,"Item OK","") | C68: Participar, com sua patrulha, de uma comemoração ou festa típica da sua região. | D68: Alterar manualmente | F68: pista 84 | G68: ='Pistas e Trilha'!A151 -> 0 | J68: =IF(G68+I68>=1,1,0)+E68 -> 0
B69: =IF(J69>0,"Item OK","") | C69: Participar, com sua patrulha, de um safari fotográfico em sua cidade, identificando os locais de importância histórica da localidade. | D69: Alterar manualmente | H69: rumo 90 | I69: ='Rumo e Travessia'!A153 -> 0 | J69: =IF(G69+I69>=1,1,0)+E69 -> 0
B70: =IF(J70>0,"Item OK","") | C70: Participar de um jantar festivo representando um estado diferente do seu. | D70: Alterar manualmente | F70: pista 85 | G70: ='Pistas e Trilha'!A152 -> 0 | H70: rumo 99 | I70: ='Rumo e Travessia'!A167 -> 0 | J70: =IF(G70+I70>=1,1,0)+E70 -> 0
B71: =IF(J71>0,"Item OK","") | C71: Aplicar jogos e atividades típicas da sua região. | D71: Alterar manualmente | F71: pista 86 | G71: ='Pistas e Trilha'!A153 -> 0 | J71: =IF(G71+I71>=1,1,0)+E71 -> 0
B72: =IF(J72>0,"Item OK","") | C72: Visitar museus, centros culturais ou pontos históricos locais para conhecer o patrimônio da região | D72: Alterar manualmente | F72: pista 84 a 87 | G72: ='Pistas e Trilha'!A150 -> 0 | J72: =IF(G72+I72>=1,1,0)+E72 -> 0
B73: =IF(J73>0,"Item OK","") | C73: Investigar lendas, histórias ou personagens do folclore brasileiro e dramatizá-los em esquetes no Fogo de Conselho | D73: Alterar manualmente | H73: rumo 92 | I73: ='Rumo e Travessia'!A157 -> 0 | J73: =IF(G73+I73>=1,1,0)+E73 -> 0
B74: =IF(J74>0,"Item OK","") | C74: Aplicar canções e danças típicas do Brasil. | D74: Alterar manualmente | H74: rumo 93 | I74: ='Rumo e Travessia'!A158 -> 0 | J74: =IF(G74+I74>=1,1,0)+E74 -> 0
B75: =IF(J75>0,"Item OK","") | C75: Confeccionar artesanato típico de alguma região do Brasil. | D75: Alterar manualmente | H75: rumo 94 | I75: ='Rumo e Travessia'!A159 -> 0 | J75: =IF(G75+I75>=1,1,0)+E75 -> 0
B76: =IF(J76>0,"Item OK","") | C76: Apresentar a cultura da sua cidade em um evento regional ou nacional, como feira das cidades ou noite folclórica. | D76: Alterar manualmente | F76: pista 84 | G76: ='Pistas e Trilha'!A151 -> 0 | H76: pista 85 | I76: ='Pistas e Trilha'!A152 -> 0 | J76: =IF(G76+I76>=1,1,0)+E76 -> 0
C77: Especialidades que podem complementar as Ações Educativas Variáveis
B78: =IF(J78>0,"Item OK","") | C78: Anime | J78: ='Especialidades ou Insígnias'!H17 -> 0
B79: =IF(J79>0,"Item OK","") | C79: Arqueologia | J79: ='Especialidades ou Insígnias'!H21 -> 0
B80: =IF(J80>0,"Item OK","") | C80: Arte da Marinharia | J80: ='Especialidades ou Insígnias'!H23 -> 0
B81: =IF(J81>0,"Item OK","") | C81: Artes Cênicas | J81: ='Especialidades ou Insígnias'!H26 -> 0
B82: =IF(J82>0,"Item OK","") | C82: Capoeira | J82: ='Especialidades ou Insígnias'!H48 -> 0
B83: =IF(J83>0,"Item OK","") | C83: Civilizações da Antiguidade | J83: ='Especialidades ou Insígnias'!H56 -> 0
B84: =IF(J84>0,"Item OK","") | C84: Cosplay | J84: ='Especialidades ou Insígnias'!H68 -> 0
B85: =IF(J85>0,"Item OK","") | C85: Culinária Típica | J85: ='Especialidades ou Insígnias'!H77 -> 0
B86: =IF(J86>0,"Item OK","") | C86: Danças Folclóricas | J86: ='Especialidades ou Insígnias'!H81 -> 0
B87: =IF(J87>0,"Item OK","") | C87: História Aeroespacial | J87: ='Especialidades ou Insígnias'!H140 -> 0
B88: =IF(J88>0,"Item OK","") | C88: História da Aviação | J88: ='Especialidades ou Insígnias'!H143 -> 0
B89: =IF(J89>0,"Item OK","") | C89: História Brasileira | J89: ='Especialidades ou Insígnias'!H141 -> 0
B90: =IF(J90>0,"Item OK","") | C90: História da Arte | J90: ='Especialidades ou Insígnias'!H142 -> 0
B91: =IF(J91>0,"Item OK","") | C91: História do Escotismo | J91: ='Especialidades ou Insígnias'!H145 -> 0
B92: =IF(J92>0,"Item OK","") | C92: História Local | J92: ='Especialidades ou Insígnias'!H146 -> 0
B93: =IF(J93>0,"Item OK","") | C93: História Marítima | J93: ='Especialidades ou Insígnias'!H147 -> 0
B94: =IF(J94>0,"Item OK","") | C94: Literatura | J94: ='Especialidades ou Insígnias'!H180 -> 0
B95: =IF(J95>0,"Item OK","") | C95: Mitologias | J95: ='Especialidades ou Insígnias'!H202 -> 0
B96: =IF(J96>0,"Item OK","") | C96: Museologia | J96: ='Especialidades ou Insígnias'!H207 -> 0
B97: =IF(J97>0,"Item OK","") | C97: Origami | J97: ='Especialidades ou Insígnias'!H217 -> 0
B98: =IF(J98>0,"Item OK","") | C98: Paleontologia | J98: ='Especialidades ou Insígnias'!H220 -> 0
B99: =IF(J99>0,"Item OK","") | C99: Poesia | J99: ='Especialidades ou Insígnias'!H234 -> 0
I100: soma | J100: =SUM(J65:J99) -> 0
C101: OU conquistar ao menos uma das seguintes especialidades a seguir no nível 2
B102: =IF(J102>0,"Item OK","") | C102: Brasilidades | J102: ='Especialidades ou Insígnias'!H44 -> 0
B103: =IF(J103>0,"Item OK","") | C103: Genealogia | J103: ='Especialidades ou Insígnias'!H130 -> 0
B104: =IF(J104>0,"Item OK","") | C104: Tradições dos Povos Originários (por equiparação a antiga Tradições Indígenas) | J104: ='Especialidades ou Insígnias'!H298 -> 0
I105: soma | J105: =SUM(J102:J104) -> 0
C107: PROMOÇÃO DA PAZ
C108: Atividades do Programa Anterior que podem complementar as atividades variáveis:
C109: Atividades Pistas e Trilha Afetivo: A65,A66, A67 Social: S71, S71, S92, S93 Espiritual: E107, E108 Atividades Rumo e Travessia Afetivo: A70, A71, A72 Social: S78, S79, S80, S99 Espiritual: E112, e113
C111: Intencionalidade Educativa | F111: BLOCO CONCLUÍDO ? | G111: =IF(B112="Bloco concluído",1,0) -> 0
B112: =IF(AND(A115="Atingiu 100% das ações fixas",A121="Atingiu 100% das ações variáveis"),"BLOCO CONCLUÍDO","") | C112: Promover a paz, a inclusão e a diversidade em suas ações diárias, respeitando e demonstrando interesse por diferentes crenças e tradições espirituais.
...

Sheet Saúde e Bem Estar
C1: SAÚDE E BEM ESTAR
C3: CUIDADO COM O CORPO | F3: Soma blocos concluídos | G3: =G7+G45+G68+G127+G169 -> 0
C4: Atividades do Programa Anterior que podem complementar as atividades variáveis:
C5: Atividades Pistas e Trilha Físico: F4, F5, F6, F7 Social: S82, S83 Atividades Rumo e Travessia Físico: F1, F2, F3, F4, F5, F6, F7
C7: Intencionalidade Educativa | F7: BLOCO CONCLUÍDO ? | G7: =IF(B8="Bloco concluído",1,0) -> 0
B8: =IF(AND(A11="Atingiu 100% das ações fixas",A19="Atingiu 100% das ações variáveis"),"BLOCO CONCLUÍDO","") | C8: Compreender e respeitar as mudanças do seu próprio corpo e das outras pessoas, independentemente de aparência, identidade ou orientação sexual. Se desafiar a superar suas limitações físicas e aprender técnicas básicas de primeiros socorros.
C10: Ações Educativas Fixas
A11: =IF(J16>=3,"Atingiu 100% das ações fixas","") | B11: =IF(J11>0,"Item OK","") | C11: Conhecer as ações iniciais em acidentes e como cuidar de: - pequenos cortes; - contusões; - escoriações; - queimaduras e - picadas de animais peçonhentos. | D11: Alterar manualmente | H11: Especialidade 1º socorros, n3 | I11: ='Especialidades ou Insígnias'!H243 -> 0 | J11: =IF(G11+I11>=1,1,0)+E11 -> 0
B12: =IF(J14>0,"Item OK","") | C12: Aplicar técnicas de bandagens e transporte de feridos. | D12: Alterar manualmente | F12: Pistas 5 | G12: ='Pistas e Trilha'!A14 -> 0 | H12: Rumo 4 a 7 | I12: ='Rumo e Travessia'!A10 -> 0 | J12: =IF(G12+I12>=1,1,0) -> 0
H13: Especialidade 1º socorros, n3 | I13: ='Especialidades ou Insígnias'!H243 -> 0 | J13: =IF(G13+I13>=1,1,0) -> 0
I14: soma | J14: =IF(G12+I12+G14>=2,1,0)+E12 -> 0
B15: =IF(J15>0,"Item OK","") | C15: Cuidar da segurança física e mental nas atividades escoteiras, respeitando os limites próprios e dos outros, e seguindo as orientações dos escotistas. | D15: Alterar manualmente | F15: Pistas 6 | G15: ='Pistas e Trilha'!A15 -> 0 | H15: Rumo 1 a 3 | I15: ='Rumo e Travessia'!A5 -> 0 | J15: =IF(G15+I15>=1,1,0)+E15 -> 0
I16: soma | J16: =J11+J14+J15 -> 0
C17: Ações Educativas Variáveis
C18: Realizar QUATRO ações dentre as listadas a seguir:
A19: =IF(OR(J39>0,J35>=4),"Atingiu 100% das ações variáveis","") | B19: =IF(J19>0,"Item OK","") | C19: Conhecer as medidas do seu corpo (palmo, envergadura, passo simples e duplo) e aplicá-las durante uma excursão com sua patrulha | D19: Alterar manualmente | F19: pistas 3 | G19: ='Pistas e Trilha'!A10 -> 0 | J19: =IF(G19+I19>=1,1,0)+E19 -> 0
B20: =IF(J20>0,"Item OK","") | C20: Participar de uma atividade, oficina, palestra que trate dos malefícios dos seguintes assuntos: anorexia, bulimia, drogas, álcool, cigarro e cigarros eletrônicos. | D20: Alterar manualmente | F20: Pistas 55 | G20: ='Pistas e Trilha'!A101 -> 0 | H20: Rumo 2 | I20: ='Rumo e Travessia'!A7 -> 0 | J20: =IF(G20+I20>=1,1,0)+E20 -> 0
B21: =IF(J21>0,"Item OK","") | C21: Saber contato dos órgãos de emergência e saber como informar os sinais vitais e situação da vítima. | D21: Alterar manualmente | F21: Especialidade 1º socorros, n3 | G21: ='Especialidades ou Insígnias'!H243 -> 0 | J21: =IF(G21+I21>=1,1,0)+E21 -> 0
B22: =IF(J22>0,"Item OK","") | C22: Participar de uma simulação de acidente e atuar em conjunto com a sua patrulha. | D22: Alterar manualmente | F22: Especialidade salvamento, n3 | G22: ='Especialidades ou Insígnias'!H265 -> 0 | H22: rumo 6 | I22: ='Rumo e Travessia'!A13 -> 0 | J22: =IF(G22+I22>=1,1,0)+E22 -> 0
B23: =IF(J23>0,"Item OK","") | C23: Proteger-se do sol e do frio durante as atividades, identificando casos de desidratação e insolação, e respeitar os limites do seu corpo. | D23: Alterar manualmente | F23: Pistas 7 | G23: ='Pistas e Trilha'!A16 -> 0 | J23: =IF(G23+I23>=1,1,0)+E23 -> 0
B24: =IF(J24>0,"Item OK","") | C24: Demonstrar como ajudar uma pessoa em casos de obstrução das vias aéreas e convulsões | D24: Alterar manualmente | F24: Especialidade 1º socorros, n3 | G24: ='Especialidades ou Insígnias'!H243 -> 0 | J24: =IF(G24+I24>=1,1,0)+E24 -> 0
B25: =IF(J25>0,"Item OK","") | C25: Conhecer os itens que compõem a caixa de primeiros socorros da patrulha e mantê-la organizada. | D25: Alterar manualmente | F25: pistas 4 | G25: ='Pistas e Trilha'!A13 -> 0 | J25: =IF(G25+I25>=1,1,0)+E25 -> 0
B26: =IF(J26>0,"Item OK","") | C26: Saber agir em casos de hemorragia. | D26: Alterar manualmente | F26: Especialidade 1º socorros, n3 | G26: ='Especialidades ou Insígnias'!H243 -> 0 | H26: Rumo 7 | I26: ='Rumo e Travessia'!A14 -> 0 | J26: =IF(G26+I26>=1,1,0)+E26 -> 0
C27: Especialidades que podem complementar as Ações Educativas Variáveis
B28: =IF(J28>0,"Item OK","") | C28: Babá | J28: ='Especialidades ou Insígnias'!H34 -> 0
B29: =IF(J29>0,"Item OK","") | C29: Cuidados com Idosos | J29: ='Especialidades ou Insígnias'!H74 -> 0
C30: Maquiagem | J30: ='Especialidades ou Insígnias'!H187 -> 0
B31: =IF(J31>0,"Item OK","") | C31: Vigilância Epidemiológica | J31: ='Especialidades ou Insígnias'!H305 -> 0
B32: =IF(J32>0,"Item OK","") | C32: Salvamento | J32: ='Especialidades ou Insígnias'!H265 -> 0
C33: Segurança e Emergência Náutica | J33: ='Especialidades ou Insígnias'!H271 -> 0
B34: =IF(J34>0,"Item OK","") | C34: Segurança | J34: ='Especialidades ou Insígnias'!H268 -> 0
C35: OU conquistar ao menos uma das seguintes especialidades a seguir no nível 2 | I35: soma | J35: =SUM(J19:J34) -> 0
B36: =IF(J36>0,"Item OK","") | C36: Anatomia Humana | J36: ='Especialidades ou Insígnias'!H14 -> 0
B37: =IF(J37>0,"Item OK","") | C37: Prevenção em Saúde | J37: ='Especialidades ou Insígnias'!H242 -> 0
B38: =IF(J38>0,"Item OK","") | C38: Primeiros Socorros | J38: ='Especialidades ou Insígnias'!H243 -> 0
I39: soma | J39: =SUM(J36:J38) -> 0
C41: ESPIRITUALIDADE
C42: Atividades do Programa Anterior que podem complementar as atividades variáveis:
C43: Atividades Pistas e Trilha Espiritual: E97, E98, E99, E103, E104, E105, E106 Atividades Rumo e Travessia Espiritual: E103, E104, E105, E106, E107, E108
C45: Intencionalidade Educativa | F45: BLOCO CONCLUÍDO ? | G45: =IF(B46="Bloco concluído",1,0) -> 0
B46: =IF(A50="Atingiu 100% das ações variáveis","BLOCO CONCLUÍDO","") | C46: Explora a espiritualidade observado as maravilhas da natureza, praticando a solidariedade e conhecendo diferentes crenças. Além disso, se esforça para viver seus princípios diariamente.
C48: Ações Educativas Variáveis
C49: Realizar QUATRO ações dentre as listadas a seguir:
A50: =IF(OR(J62>0,J58>=4),"Atingiu 100% das ações variáveis","") | B50: =IF(J50>0,"Item OK","") | C50: Fazer reflexões espirituais rotineiras na tropa ou patrulha, ao ar livre. | D50: Alterar manualmente | F50: Pistas 99 | G50: ='Pistas e Trilha'!A175 -> 0 | J50: =IF(G50+I50>=1,1,0)+E50 -> 0
B51: =IF(J51>0,"Item OK","") | C51: Apresentar um pequeno relato à patrulha ou tropa sobre os ensinamentos de sua crença ou religião | D51: Alterar manualmente | F51: Pistas 102 | G51: ='Pistas e Trilha'!A180 -> 0 | J51: =IF(G51+I51>=1,1,0)+E51 -> 0
B52: =IF(J52>0,"Item OK","") | C52: Auxiliar na realização de uma celebração de sua comunidade religiosa. | D52: Alterar manualmente | F52: Pistas 98 | G52: ='Pistas e Trilha'!A174 -> 0 | J52: =IF(G52+I52>=1,1,0)+E52 -> 0
B53: =IF(J55>0,"Item OK","") | C53: Celebrar sua crença ou religião regularmente. | D53: Alterar manualmente | F53: Pistas 105 | G53: ='Pistas e Trilha'!A185 -> 0 | H53: Rumo 103 | I53: ='Rumo e Travessia'!A182 -> 0 | J53: =IF(G53+I53>=1,1,0) -> 0
H54: Rumo 109 | I54: ='Rumo e Travessia'!A192 -> 0 | J54: =IF(G54+I54>=1,1,0) -> 0
I55: soma | J55: =IF(G53+I53+G54+I54>=1,1,0)+E53 -> 0
B56: =IF(J56>0,"Item OK","") | C56: Colaborar na organização de um culto interconfessional em uma atividade escoteira. | D56: Alterar manualmente | F56: Pista 108 | G56: ='Pistas e Trilha'!A190 -> 0 | J56: =IF(G56+I56>=1,1,0)+E56 -> 0
B57: =IF(J57>0,"Item OK","") | C57: Participar de um momento de reflexão e conexão com um ambiente natural em que possa apreciar e agradecer a beleza do mundo natural. | D57: Alterar manualmente | F57: Pistas 103 | G57: ='Pistas e Trilha'!A183 -> 0 | H57: Rumo 106 | I57: ='Rumo e Travessia'!A187 -> 0 | J57: =IF(G57+I57>=1,1,0)+E57 -> 0
I58: soma | J58: =J50+J51+J52+J55+J56+J57 -> 0
C59: OU conquistar ao menos uma das seguintes especialidades a seguir no nível 2 ou Insígnia
B60: =IF(J60>0,"Item OK","") | C60: Yoga | J60: ='Especialidades ou Insígnias'!H310 -> 0
B61: =IF(J61>0,"Item OK","") | C61: Diálogo Inter-religioso | J61: ='Especialidades ou Insígnias'!H87 -> 0
I62: soma | J62: =SUM(J60:J61) -> 0
C64: HÁBITOS SAUDÁVEIS
C65: Atividades do Programa Anterior que podem complementar as atividades variáveis:
C66: Atividades Pistas e Trilha Físico: F2, F3, F8, F9, F10, F11, F2, F13, F14, F15, F19, F20 Atividades Rumo e Travessia Físico: F8, F9, F10, F11, F12, F13, F14, F19, F20
C68: Intencionalidade Educativa | F68: BLOCO CONCLUÍDO ? | G68: =IF(B69="Bloco concluído",1,0) -> 0
B69: =IF(AND(A72="Atingiu 100% das ações fixas",A77="Atingiu 100% das ações variáveis"),"BLOCO CONCLUÍDO","") | C69: Cuidar da própria saúde praticando exercícios físicos, mantendo uma alimentação equilibrada e garantindo bons hábitos de higiene pessoal e organização do seu espaço.
C71: Ações Educativas Fixas
A72: =IF(J74>=2,"Atingiu 100% das ações fixas","") | B72: =IF(J72>0,"Item OK","") | C72: Planejar e executar um cardápio completo e saudável (café da manhã, almoço e jantar) para a patrulha em acampamento. | D72: Alterar manualmente | F72: Pistas 12 | G72: ='Pistas e Trilha'!A25 -> 0 | H72: Rumo 13 | I72: ='Rumo e Travessia'!A24 -> 0 | J72: =IF(G72+I72>=1,1,0)+E72 -> 0
B73: =IF(J73>0,"Item OK","") | C73: Conhecer e aplicar normas de limpeza no tratamento e conservação de alimentos nas atividades de patrulha | D73: Alterar manualmente | H73: Rumo 14 | I73: ='Rumo e Travessia'!A25 -> 0 | J73: =IF(G73+I73>=1,1,0)+E73 -> 0
I74: soma | J74: =SUM(J72:J73) -> 0
C75: Ações Educativas Variáveis
C76: Realizar TRÊS ações dentre as listadas a seguir:
A77: =IF(OR(J121>0,J118>=3),"Atingiu 100% das ações variáveis","") | B77: =IF(J77>0,"Item OK","") | C77: Manter hábitos de higiene pessoal, utilizar o vestuário ou uniforme adequadamente, demonstrando aplicação correta dos distintivos. | D77: Alterar manualmente | F77: pistas 8 | G77: ='Pistas e Trilha'!A19 -> 0 | H77: rumo 10 | I77: ='Rumo e Travessia'!A19 -> 0 | J77: =IF(G77+I77>=1,1,0)+E77 -> 0
B78: =IF(J80>0,"Item OK","") | C78: Contribuir para manter a sede do grupo e canto de patrulha em ordem e em perfeito estado de conservação. | D78: Alterar manualmente | F78: Pistas 10 | G78: ='Pistas e Trilha'!A21 -> 0 | H78: Rumo 8 | I78: ='Rumo e Travessia'!A17 -> 0
F79: Pistas 53 | G79: ='Pistas e Trilha'!A96 -> 0
I80: soma | J80: =IF(G78+I78+G79+I79>=2,1,0)+E78 -> 0
B81: =IF(J83>0,"Item OK","") | C81: Montar um cronograma semanal, equilibrando estudos, responsabilidades e momentos de lazer. | D81: Alterar manualmente | F81: Pistas 16 | G81: ='Pistas e Trilha'!A31 -> 0 | H81: Rumo 15 | I81: ='Rumo e Travessia'!A28 -> 0
F82: Pistas 17 | G82: ='Pistas e Trilha'!A32 -> 0 | H82: Rumo 16 | I82: ='Rumo e Travessia'!A29 -> 0
I83: soma | J83: =IF(G81+I81+G82+I82>=3,1,0)+E81 -> 0
B84: =IF(J84>0,"Item OK","") | C84: Praticar uma atividade física regularmente. | D84: Alterar manualmente | F84: Pistas 19 | G84: ='Pistas e Trilha'!A36 -> 0 | H84: Rumo 19 | I84: ='Rumo e Travessia'!A34 -> 0 | J84: =IF(G84+I84>=1,1,0)+E84 -> 0
B85: =IF(J85>0,"Item OK","") | C85: Promover um piquenique com alimentos saudáveis com sua patrulha ou tropa. | D85: Alterar manualmente | F85: Pista 12 a 15 | G85: ='Pistas e Trilha'!A24 -> 0 | H85: Rumo 12 a 14 | I85: ='Rumo e Travessia'!A22 -> 0 | J85: =IF(G85+I85>=1,1,0)+E85 -> 0
B86: =IF(J86>0,"Item OK","") | C86: Manter adequada rotina de sono e alimentação saudável | D86: Alterar manualmente | F86: Pista 1 a 3 | G86: ='Pistas e Trilha'!A7 -> 0 | H86: Rumo 1 a 3 | I86: ='Rumo e Travessia'!A5 -> 0 | J86: =IF(G86+I86>=1,1,0)+E86 -> 0
B87: =IF(J87>0,"Item OK","") | C87: Saber o que são as indicações de rótulos, o que são gorduras saturadas, conservantes, corantes além dos selos de advertência. | D87: Alterar manualmente | J87: =IF(G87+I87>=1,1,0)+E87 -> 0
B88: =IF(J88>0,"Item OK","") | C88: Arrumar e limpar seu quarto e contribuir nas rotinas da casa. | D88: Alterar manualmente | F88: Pistas 66 | G88: ='Pistas e Trilha'!A118 -> 0 | J88: =IF(G88+I88>=1,1,0)+E88 -> 0
C89: Especialidades que podem complementar as Ações Educativas Variáveis
B90: =IF(J90>0,"Item OK","") | C90: Artes Marciais | J90: ='Especialidades ou Insígnias'!H29 -> 0
B91: =IF(J91>0,"Item OK","") | C91: Canoagem | J91: ='Especialidades ou Insígnias'!H46 -> 0
B92: =IF(J92>0,"Item OK","") | C92: Ciclismo | J92: ='Especialidades ou Insígnias'!H52 -> 0
B93: =IF(J93>0,"Item OK","") | C93: Corrida de Rua | J93: ='Especialidades ou Insígnias'!H67 -> 0
B94: =IF(J94>0,"Item OK","") | C94: Culinária Vegetariana | J94: ='Especialidades ou Insígnias'!H78 -> 0
B95: =IF(J95>0,"Item OK","") | C95: Cuidados Bucais | J95: ='Especialidades ou Insígnias'!H73 -> 0
B96: =IF(J96>0,"Item OK","") | C96: Dança | J96: ='Especialidades ou Insígnias'!H80 -> 0
B97: =IF(J97>0,"Item OK","") | C97: Desportos Inclusivos | J97: ='Especialidades ou Insígnias'!H86 -> 0
B98: =IF(J98>0,"Item OK","") | C98: Esportes de Quadra (equiparada com as antigas Handebol e Voleibol) | J98: =IF('Especialidades ou Insígnias'!H135+'Especialidades ou Insígnias'!H307>=1,1,0) -> 0
B99: =IF(J99>0,"Item OK","") | C99: Futebol | J99: ='Especialidades ou Insígnias'!H122 -> 0
B100: =IF(J100>0,"Item OK","") | C100: Ginásticas (equiparada com as antigas Ginástica e Ginástica Rítmica) | J100: =IF(J101+J101>=1,1,0) -> 0
C101: Ginástica | J101: ='Especialidades ou Insígnias'!H131 -> 0
C102: Ginástica Rítmica | J102: ='Especialidades ou Insígnias'!H132 -> 0
B103: =IF(J103>0,"Item OK","") | C103: Hipismo | J103: ='Especialidades ou Insígnias'!H138 -> 0
B104: =IF(J104>0,"Item OK","") | C104: Mergulho | J104: ='Especialidades ou Insígnias'!H196 -> 0
B105: =IF(J105>0,"Item OK","") | C105: Natação | J105: ='Especialidades ou Insígnias'!H209 -> 0
B106: =IF(J106>0,"Item OK","") | C106: Patinação | J106: ='Especialidades ou Insígnias'!H223 -> 0
B107: =IF(J107>0,"Item OK","") | C107: Plantas Medicinais | J107: ='Especialidades ou Insígnias'!H232 -> 0
B108: =IF(J108>0,"Item OK","") | C108: Remo | J108: ='Especialidades ou Insígnias'!H259 -> 0
B109: =IF(J109>0,"Item OK","") | C109: Skateboard | J109: ='Especialidades ou Insígnias'!H279 -> 0
...
